{
  "235716": {
    "x": 1072,
    "y": 532,
    "visible": true,
    "action": "air"
  },
  "235717": {
    "x": 1068,
    "y": 528,
    "visible": true,
    "action": "air"
  },
  "235718": {
    "x": 1065,
    "y": 526,
    "visible": true,
    "action": "air"
  },
  "235719": {
    "x": 1063,
    "y": 524,
    "visible": true,
    "action": "air"
  },
  "235720": {
    "x": 1059,
    "y": 522,
    "visible": true,
    "action": "air"
  },
  "235721": {
    "x": 1056,
    "y": 521,
    "visible": true,
    "action": "air"
  },
  "235722": {
    "x": 1055,
    "y": 519,
    "visible": true,
    "action": "air"
  },
  "235723": {
    "x": 1051,
    "y": 518,
    "visible": true,
    "action": "air"
  },
  "235724": {
    "x": 1046,
    "y": 519,
    "visible": true,
    "action": "air"
  },
  "235725": {
    "x": 1045,
    "y": 518,
    "visible": true,
    "action": "air"
  },
  "235726": {
    "x": 1041,
    "y": 519,
    "visible": true,
    "action": "air"
  },
  "235727": {
    "x": 1037,
    "y": 521,
    "visible": true,
    "action": "air"
  },
  "235728": {
    "x": 1036,
    "y": 521,
    "visible": true,
    "action": "air"
  },
  "235729": {
    "x": 1033,
    "y": 524,
    "visible": true,
    "action": "air"
  },
  "235730": {
    "x": 1029,
    "y": 527,
    "visible": true,
    "action": "air"
  },
  "235731": {
    "x": 1027,
    "y": 528,
    "visible": true,
    "action": "air"
  },
  "235732": {
    "x": 1025,
    "y": 532,
    "visible": true,
    "action": "air"
  },
  "235733": {
    "x": 1022,
    "y": 537,
    "visible": true,
    "action": "air"
  },
  "235734": {
    "x": 1016,
    "y": 539,
    "visible": true,
    "action": "air"
  },
  "235735": {
    "x": 1013,
    "y": 545,
    "visible": true,
    "action": "air"
  },
  "235736": {
    "x": 1012,
    "y": 551,
    "visible": true,
    "action": "air"
  },
  "235737": {
    "x": 1011.7277227722772,
    "y": 546.3316831683167,
    "visible": true,
    "action": "hit"
  },
  "235738": {
    "x": 1003,
    "y": 531,
    "visible": true,
    "action": "air"
  },
  "235739": {
    "x": 999,
    "y": 515,
    "visible": true,
    "action": "air"
  },
  "235740": {
    "x": 993,
    "y": 504,
    "visible": true,
    "action": "air"
  },
  "235741": {
    "x": 985,
    "y": 491,
    "visible": true,
    "action": "air"
  },
  "235742": {
    "x": 979,
    "y": 481,
    "visible": true,
    "action": "air"
  },
  "235743": {
    "x": 976,
    "y": 474,
    "visible": true,
    "action": "air"
  },
  "235744": {
    "x": 967,
    "y": 465,
    "visible": true,
    "action": "air"
  },
  "235745": {
    "x": 963,
    "y": 458,
    "visible": true,
    "action": "air"
  },
  "235746": {
    "x": 955,
    "y": 454,
    "visible": true,
    "action": "air"
  },
  "235747": {
    "x": 952,
    "y": 449,
    "visible": true,
    "action": "air"
  },
  "235748": {
    "x": 945,
    "y": 446,
    "visible": true,
    "action": "air"
  },
  "235749": {
    "x": 940,
    "y": 443,
    "visible": true,
    "action": "air"
  },
  "235750": {
    "x": 934,
    "y": 440,
    "visible": true,
    "action": "air"
  },
  "235751": {
    "x": 925,
    "y": 439,
    "visible": true,
    "action": "air"
  },
  "235752": {
    "x": 921,
    "y": 437,
    "visible": true,
    "action": "air"
  },
  "235753": {
    "x": 917,
    "y": 437,
    "visible": true,
    "action": "air"
  },
  "235754": {
    "x": 909,
    "y": 438,
    "visible": true,
    "action": "air"
  },
  "235755": {
    "x": 905,
    "y": 438,
    "visible": true,
    "action": "air"
  },
  "235756": {
    "x": 896,
    "y": 440,
    "visible": true,
    "action": "air"
  },
  "235757": {
    "x": 893,
    "y": 441,
    "visible": true,
    "action": "air"
  },
  "235758": {
    "x": 888,
    "y": 443,
    "visible": true,
    "action": "air"
  },
  "235759": {
    "x": 882,
    "y": 446,
    "visible": true,
    "action": "air"
  },
  "235760": {
    "x": 876,
    "y": 448,
    "visible": true,
    "action": "air"
  },
  "235761": {
    "x": 869.4009900990098,
    "y": 452.2722772277225,
    "visible": true,
    "action": "bounce"
  },
  "235762": {
    "x": 867,
    "y": 433,
    "visible": true,
    "action": "air"
  },
  "235763": {
    "x": 866,
    "y": 416,
    "visible": true,
    "action": "air"
  },
  "235764": {
    "x": 866,
    "y": 401,
    "visible": true,
    "action": "air"
  },
  "235765": {
    "x": 865,
    "y": 387,
    "visible": true,
    "action": "air"
  },
  "235766": {
    "x": 863,
    "y": 374,
    "visible": true,
    "action": "air"
  },
  "235767": {
    "x": 862,
    "y": 361,
    "visible": true,
    "action": "air"
  },
  "235768": {
    "x": 862,
    "y": 348,
    "visible": true,
    "action": "air"
  },
  "235769": {
    "x": 861,
    "y": 338,
    "visible": true,
    "action": "air"
  },
  "235770": {
    "x": 858,
    "y": 328,
    "visible": true,
    "action": "air"
  },
  "235771": {
    "x": 859,
    "y": 315,
    "visible": true,
    "action": "air"
  },
  "235772": {
    "x": 857,
    "y": 305,
    "visible": true,
    "action": "air"
  },
  "235773": {
    "x": 855,
    "y": 296,
    "visible": true,
    "action": "air"
  },
  "235774": {
    "x": 855,
    "y": 288,
    "visible": true,
    "action": "air"
  },
  "235775": {
    "x": 852,
    "y": 279,
    "visible": true,
    "action": "air"
  },
  "235776": {
    "x": 849,
    "y": 274,
    "visible": true,
    "action": "air"
  },
  "235777": {
    "x": 850,
    "y": 265,
    "visible": true,
    "action": "air"
  },
  "235778": {
    "x": 849,
    "y": 258,
    "visible": true,
    "action": "air"
  },
  "235779": {
    "x": null,
    "y": null,
    "visible": false,
    "action": "air"
  },
  "235780": {
    "x": 846,
    "y": 246,
    "visible": true,
    "action": "air"
  },
  "235781": {
    "x": 847,
    "y": 250,
    "visible": true,
    "action": "air"
  },
  "235782": {
    "x": null,
    "y": null,
    "visible": false,
    "action": "air"
  },
  "235783": {
    "x": null,
    "y": null,
    "visible": false,
    "action": "air"
  },
  "235784": {
    "x": null,
    "y": null,
    "visible": false,
    "action": "air"
  },
  "235785": {
    "x": null,
    "y": null,
    "visible": false,
    "action": "air"
  },
  "235786": {
    "x": null,
    "y": null,
    "visible": false,
    "action": "air"
  },
  "235787": {
    "x": null,
    "y": null,
    "visible": false,
    "action": "air"
  },
  "235788": {
    "x": null,
    "y": null,
    "visible": false,
    "action": "air"
  },
  "235789": {
    "x": null,
    "y": null,
    "visible": false,
    "action": "air"
  },
  "235790": {
    "x": null,
    "y": null,
    "visible": false,
    "action": "air"
  },
  "235791": {
    "x": null,
    "y": null,
    "visible": false,
    "action": "air"
  },
  "235792": {
    "x": null,
    "y": null,
    "visible": false,
    "action": "air"
  },
  "235793": {
    "x": null,
    "y": null,
    "visible": false,
    "action": "air"
  },
  "235794": {
    "x": null,
    "y": null,
    "visible": false,
    "action": "air"
  },
  "235795": {
    "x": null,
    "y": null,
    "visible": false,
    "action": "air"
  },
  "235796": {
    "x": null,
    "y": null,
    "visible": false,
    "action": "air"
  },
  "235797": {
    "x": null,
    "y": null,
    "visible": false,
    "action": "air"
  },
  "235798": {
    "x": null,
    "y": null,
    "visible": false,
    "action": "air"
  },
  "235799": {
    "x": null,
    "y": null,
    "visible": false,
    "action": "air"
  },
  "235800": {
    "x": null,
    "y": null,
    "visible": false,
    "action": "air"
  },
  "235801": {
    "x": 819.8960396039603,
    "y": 210.93564356435604,
    "visible": true,
    "action": "hit"
  },
  "235802": {
    "x": null,
    "y": null,
    "visible": false,
    "action": "air"
  },
  "235803": {
    "x": 829,
    "y": 207,
    "visible": true,
    "action": "air"
  },
  "235804": {
    "x": 834,
    "y": 208,
    "visible": true,
    "action": "air"
  },
  "235805": {
    "x": 842,
    "y": 208,
    "visible": true,
    "action": "air"
  },
  "235806": {
    "x": 843,
    "y": 207,
    "visible": true,
    "action": "air"
  },
  "235807": {
    "x": 849,
    "y": 208,
    "visible": true,
    "action": "air"
  },
  "235808": {
    "x": 858,
    "y": 212,
    "visible": true,
    "action": "air"
  },
  "235809": {
    "x": null,
    "y": null,
    "visible": false,
    "action": "air"
  },
  "235810": {
    "x": null,
    "y": null,
    "visible": false,
    "action": "air"
  },
  "235811": {
    "x": null,
    "y": null,
    "visible": false,
    "action": "air"
  },
  "235812": {
    "x": null,
    "y": null,
    "visible": false,
    "action": "air"
  },
  "235813": {
    "x": null,
    "y": null,
    "visible": false,
    "action": "air"
  },
  "235814": {
    "x": null,
    "y": null,
    "visible": false,
    "action": "air"
  },
  "235815": {
    "x": null,
    "y": null,
    "visible": false,
    "action": "air"
  },
  "235816": {
    "x": null,
    "y": null,
    "visible": false,
    "action": "air"
  },
  "235817": {
    "x": null,
    "y": null,
    "visible": false,
    "action": "air"
  },
  "235818": {
    "x": 906,
    "y": 244,
    "visible": true,
    "action": "air"
  },
  "235819": {
    "x": 912,
    "y": 251,
    "visible": true,
    "action": "air"
  },
  "235820": {
    "x": null,
    "y": null,
    "visible": false,
    "action": "air"
  },
  "235821": {
    "x": 921,
    "y": 267,
    "visible": true,
    "action": "air"
  },
  "235822": {
    "x": 926,
    "y": 274,
    "visible": true,
    "action": "air"
  },
  "235823": {
    "x": 934,
    "y": 284,
    "visible": true,
    "action": "air"
  },
  "235824": {
    "x": 937,
    "y": 292,
    "visible": true,
    "action": "air"
  },
  "235825": {
    "x": 941,
    "y": 302,
    "visible": true,
    "action": "air"
  },
  "235826": {
    "x": 948,
    "y": 314,
    "visible": true,
    "action": "air"
  },
  "235827": {
    "x": 952,
    "y": 324,
    "visible": true,
    "action": "air"
  },
  "235828": {
    "x": 955,
    "y": 336,
    "visible": true,
    "action": "air"
  },
  "235829": {
    "x": 963,
    "y": 349,
    "visible": true,
    "action": "air"
  },
  "235830": {
    "x": 966,
    "y": 362,
    "visible": true,
    "action": "air"
  },
  "235831": {
    "x": 970,
    "y": 376,
    "visible": true,
    "action": "air"
  },
  "235832": {
    "x": 977,
    "y": 394,
    "visible": true,
    "action": "air"
  },
  "235833": {
    "x": 980,
    "y": 407,
    "visible": true,
    "action": "air"
  },
  "235834": {
    "x": 984,
    "y": 423,
    "visible": true,
    "action": "air"
  },
  "235835": {
    "x": 992,
    "y": 441,
    "visible": true,
    "action": "air"
  },
  "235836": {
    "x": 996,
    "y": 456,
    "visible": true,
    "action": "air"
  },
  "235837": {
    "x": 1000,
    "y": 476,
    "visible": true,
    "action": "air"
  },
  "235838": {
    "x": 1003,
    "y": 497,
    "visible": true,
    "action": "air"
  },
  "235839": {
    "x": 1008,
    "y": 517,
    "visible": true,
    "action": "air"
  },
  "235840": {
    "x": 1013,
    "y": 537,
    "visible": true,
    "action": "air"
  },
  "235841": {
    "x": 1016,
    "y": 562,
    "visible": true,
    "action": "air"
  },
  "235842": {
    "x": 1024,
    "y": 582,
    "visible": true,
    "action": "air"
  },
  "235843": {
    "x": 1029,
    "y": 607,
    "visible": true,
    "action": "air"
  },
  "235844": {
    "x": 1033,
    "y": 635,
    "visible": true,
    "action": "air"
  },
  "235845": {
    "x": 1038,
    "y": 657,
    "visible": true,
    "action": "air"
  },
  "235846": {
    "x": 1042,
    "y": 688,
    "visible": true,
    "action": "air"
  },
  "235847": {
    "x": 1046,
    "y": 715,
    "visible": true,
    "action": "air"
  },
  "235848": {
    "x": 1054,
    "y": 741,
    "visible": true,
    "action": "air"
  },
  "235849": {
    "x": 1057,
    "y": 772,
    "visible": true,
    "action": "air"
  },
  "235850": {
    "x": 1062,
    "y": 802,
    "visible": true,
    "action": "air"
  },
  "235851": {
    "x": 1066,
    "y": 831,
    "visible": true,
    "action": "air"
  },
  "235852": {
    "x": 1071,
    "y": 864,
    "visible": true,
    "action": "air"
  },
  "235853": {
    "x": 1076,
    "y": 906,
    "visible": true,
    "action": "air"
  },
  "235854": {
    "x": null,
    "y": null,
    "visible": false,
    "action": "air"
  },
  "235855": {
    "x": null,
    "y": null,
    "visible": false,
    "action": "air"
  },
  "235856": {
    "x": 1085.9851485148515,
    "y": 979.4999999999998,
    "visible": true,
    "action": "bounce"
  },
  "235857": {
    "x": null,
    "y": null,
    "visible": false,
    "action": "air"
  },
  "235858": {
    "x": null,
    "y": null,
    "visible": false,
    "action": "air"
  },
  "235859": {
    "x": null,
    "y": null,
    "visible": false,
    "action": "air"
  },
  "235860": {
    "x": null,
    "y": null,
    "visible": false,
    "action": "air"
  },
  "235861": {
    "x": null,
    "y": null,
    "visible": false,
    "action": "air"
  },
  "235862": {
    "x": null,
    "y": null,
    "visible": false,
    "action": "air"
  },
  "235863": {
    "x": null,
    "y": null,
    "visible": false,
    "action": "air"
  },
  "235864": {
    "x": 1096,
    "y": 1024,
    "visible": true,
    "action": "air"
  },
  "235865": {
    "x": null,
    "y": null,
    "visible": false,
    "action": "air"
  },
  "235866": {
    "x": null,
    "y": null,
    "visible": false,
    "action": "air"
  },
  "235867": {
    "x": null,
    "y": null,
    "visible": false,
    "action": "air"
  },
  "235868": {
    "x": null,
    "y": null,
    "visible": false,
    "action": "air"
  },
  "235869": {
    "x": null,
    "y": null,
    "visible": false,
    "action": "air"
  },
  "235870": {
    "x": null,
    "y": null,
    "visible": false,
    "action": "air"
  },
  "235871": {
    "x": null,
    "y": null,
    "visible": false,
    "action": "air"
  },
  "235872": {
    "x": null,
    "y": null,
    "visible": false,
    "action": "air"
  },
  "235873": {
    "x": null,
    "y": null,
    "visible": false,
    "action": "air"
  },
  "235874": {
    "x": null,
    "y": null,
    "visible": false,
    "action": "air"
  },
  "235875": {
    "x": null,
    "y": null,
    "visible": false,
    "action": "air"
  },
  "235876": {
    "x": 1074,
    "y": 988,
    "visible": true,
    "action": "air"
  },
  "235877": {
    "x": 1071,
    "y": 983,
    "visible": true,
    "action": "air"
  },
  "235878": {
    "x": null,
    "y": null,
    "visible": false,
    "action": "air"
  },
  "235879": {
    "x": null,
    "y": null,
    "visible": false,
    "action": "air"
  },
  "235880": {
    "x": null,
    "y": null,
    "visible": false,
    "action": "air"
  },
  "235881": {
    "x": null,
    "y": null,
    "visible": false,
    "action": "air"
  },
  "235882": {
    "x": null,
    "y": null,
    "visible": false,
    "action": "air"
  },
  "235883": {
    "x": null,
    "y": null,
    "visible": false,
    "action": "air"
  },
  "235884": {
    "x": 998,
    "y": 890,
    "visible": true,
    "action": "air"
  },
  "235885": {
    "x": null,
    "y": null,
    "visible": false,
    "action": "air"
  },
  "235886": {
    "x": null,
    "y": null,
    "visible": false,
    "action": "air"
  },
  "235887": {
    "x": null,
    "y": null,
    "visible": false,
    "action": "air"
  },
  "235888": {
    "x": null,
    "y": null,
    "visible": false,
    "action": "air"
  },
  "235889": {
    "x": null,
    "y": null,
    "visible": false,
    "action": "air"
  },
  "235890": {
    "x": null,
    "y": null,
    "visible": false,
    "action": "air"
  },
  "235891": {
    "x": null,
    "y": null,
    "visible": false,
    "action": "air"
  },
  "235892": {
    "x": null,
    "y": null,
    "visible": false,
    "action": "air"
  },
  "235893": {
    "x": null,
    "y": null,
    "visible": false,
    "action": "air"
  },
  "235894": {
    "x": null,
    "y": null,
    "visible": false,
    "action": "air"
  },
  "235895": {
    "x": null,
    "y": null,
    "visible": false,
    "action": "air"
  },
  "235896": {
    "x": null,
    "y": null,
    "visible": false,
    "action": "air"
  },
  "235897": {
    "x": null,
    "y": null,
    "visible": false,
    "action": "air"
  },
  "235898": {
    "x": null,
    "y": null,
    "visible": false,
    "action": "air"
  },
  "235899": {
    "x": null,
    "y": null,
    "visible": false,
    "action": "air"
  },
  "235900": {
    "x": null,
    "y": null,
    "visible": false,
    "action": "air"
  },
  "235901": {
    "x": null,
    "y": null,
    "visible": false,
    "action": "air"
  },
  "235902": {
    "x": null,
    "y": null,
    "visible": false,
    "action": "air"
  },
  "235903": {
    "x": null,
    "y": null,
    "visible": false,
    "action": "air"
  },
  "235904": {
    "x": null,
    "y": null,
    "visible": false,
    "action": "air"
  },
  "235905": {
    "x": null,
    "y": null,
    "visible": false,
    "action": "air"
  },
  "235906": {
    "x": null,
    "y": null,
    "visible": false,
    "action": "air"
  },
  "235907": {
    "x": null,
    "y": null,
    "visible": false,
    "action": "air"
  },
  "235908": {
    "x": null,
    "y": null,
    "visible": false,
    "action": "air"
  },
  "235909": {
    "x": null,
    "y": null,
    "visible": false,
    "action": "air"
  },
  "235910": {
    "x": null,
    "y": null,
    "visible": false,
    "action": "air"
  },
  "235911": {
    "x": null,
    "y": null,
    "visible": false,
    "action": "air"
  },
  "235912": {
    "x": null,
    "y": null,
    "visible": false,
    "action": "air"
  },
  "235913": {
    "x": null,
    "y": null,
    "visible": false,
    "action": "air"
  },
  "235914": {
    "x": null,
    "y": null,
    "visible": false,
    "action": "air"
  },
  "235915": {
    "x": null,
    "y": null,
    "visible": false,
    "action": "air"
  },
  "235916": {
    "x": null,
    "y": null,
    "visible": false,
    "action": "air"
  },
  "235917": {
    "x": null,
    "y": null,
    "visible": false,
    "action": "air"
  },
  "235918": {
    "x": null,
    "y": null,
    "visible": false,
    "action": "air"
  },
  "235919": {
    "x": null,
    "y": null,
    "visible": false,
    "action": "air"
  },
  "235920": {
    "x": null,
    "y": null,
    "visible": false,
    "action": "air"
  }
}