{
  "957600": {
    "x": null,
    "y": null,
    "visible": false,
    "action": "air"
  },
  "957601": {
    "x": null,
    "y": null,
    "visible": false,
    "action": "air"
  },
  "957602": {
    "x": null,
    "y": null,
    "visible": false,
    "action": "air"
  },
  "957603": {
    "x": null,
    "y": null,
    "visible": false,
    "action": "air"
  },
  "957604": {
    "x": null,
    "y": null,
    "visible": false,
    "action": "air"
  },
  "957605": {
    "x": null,
    "y": null,
    "visible": false,
    "action": "air"
  },
  "957606": {
    "x": null,
    "y": null,
    "visible": false,
    "action": "air"
  },
  "957607": {
    "x": null,
    "y": null,
    "visible": false,
    "action": "air"
  },
  "957608": {
    "x": null,
    "y": null,
    "visible": false,
    "action": "air"
  },
  "957609": {
    "x": null,
    "y": null,
    "visible": false,
    "action": "air"
  },
  "957610": {
    "x": null,
    "y": null,
    "visible": false,
    "action": "air"
  },
  "957611": {
    "x": null,
    "y": null,
    "visible": false,
    "action": "air"
  },
  "957612": {
    "x": null,
    "y": null,
    "visible": false,
    "action": "air"
  },
  "957613": {
    "x": null,
    "y": null,
    "visible": false,
    "action": "air"
  },
  "957614": {
    "x": null,
    "y": null,
    "visible": false,
    "action": "air"
  },
  "957615": {
    "x": null,
    "y": null,
    "visible": false,
    "action": "air"
  },
  "957616": {
    "x": null,
    "y": null,
    "visible": false,
    "action": "air"
  },
  "957617": {
    "x": null,
    "y": null,
    "visible": false,
    "action": "air"
  },
  "957618": {
    "x": null,
    "y": null,
    "visible": false,
    "action": "air"
  },
  "957619": {
    "x": null,
    "y": null,
    "visible": false,
    "action": "air"
  },
  "957620": {
    "x": null,
    "y": null,
    "visible": false,
    "action": "air"
  },
  "957621": {
    "x": null,
    "y": null,
    "visible": false,
    "action": "air"
  },
  "957622": {
    "x": null,
    "y": null,
    "visible": false,
    "action": "air"
  },
  "957623": {
    "x": null,
    "y": null,
    "visible": false,
    "action": "air"
  },
  "957624": {
    "x": null,
    "y": null,
    "visible": false,
    "action": "air"
  },
  "957625": {
    "x": null,
    "y": null,
    "visible": false,
    "action": "air"
  },
  "957626": {
    "x": null,
    "y": null,
    "visible": false,
    "action": "air"
  },
  "957627": {
    "x": null,
    "y": null,
    "visible": false,
    "action": "air"
  },
  "957628": {
    "x": null,
    "y": null,
    "visible": false,
    "action": "air"
  },
  "957629": {
    "x": null,
    "y": null,
    "visible": false,
    "action": "air"
  },
  "957630": {
    "x": null,
    "y": null,
    "visible": false,
    "action": "air"
  },
  "957631": {
    "x": null,
    "y": null,
    "visible": false,
    "action": "air"
  },
  "957632": {
    "x": null,
    "y": null,
    "visible": false,
    "action": "air"
  },
  "957633": {
    "x": null,
    "y": null,
    "visible": false,
    "action": "air"
  },
  "957634": {
    "x": null,
    "y": null,
    "visible": false,
    "action": "air"
  },
  "957635": {
    "x": null,
    "y": null,
    "visible": false,
    "action": "air"
  },
  "957636": {
    "x": null,
    "y": null,
    "visible": false,
    "action": "air"
  },
  "957637": {
    "x": null,
    "y": null,
    "visible": false,
    "action": "air"
  },
  "957638": {
    "x": null,
    "y": null,
    "visible": false,
    "action": "air"
  },
  "957639": {
    "x": null,
    "y": null,
    "visible": false,
    "action": "air"
  },
  "957640": {
    "x": null,
    "y": null,
    "visible": false,
    "action": "air"
  },
  "957641": {
    "x": null,
    "y": null,
    "visible": false,
    "action": "air"
  },
  "957642": {
    "x": null,
    "y": null,
    "visible": false,
    "action": "air"
  },
  "957643": {
    "x": null,
    "y": null,
    "visible": false,
    "action": "air"
  },
  "957644": {
    "x": null,
    "y": null,
    "visible": false,
    "action": "air"
  },
  "957645": {
    "x": null,
    "y": null,
    "visible": false,
    "action": "air"
  },
  "957646": {
    "x": null,
    "y": null,
    "visible": false,
    "action": "air"
  },
  "957647": {
    "x": null,
    "y": null,
    "visible": false,
    "action": "air"
  },
  "957648": {
    "x": null,
    "y": null,
    "visible": false,
    "action": "air"
  },
  "957649": {
    "x": null,
    "y": null,
    "visible": false,
    "action": "air"
  },
  "957650": {
    "x": null,
    "y": null,
    "visible": false,
    "action": "air"
  },
  "957651": {
    "x": null,
    "y": null,
    "visible": false,
    "action": "air"
  },
  "957652": {
    "x": null,
    "y": null,
    "visible": false,
    "action": "air"
  },
  "957653": {
    "x": null,
    "y": null,
    "visible": false,
    "action": "air"
  },
  "957654": {
    "x": null,
    "y": null,
    "visible": false,
    "action": "air"
  },
  "957655": {
    "x": null,
    "y": null,
    "visible": false,
    "action": "air"
  },
  "957656": {
    "x": null,
    "y": null,
    "visible": false,
    "action": "air"
  },
  "957657": {
    "x": null,
    "y": null,
    "visible": false,
    "action": "air"
  },
  "957658": {
    "x": null,
    "y": null,
    "visible": false,
    "action": "air"
  },
  "957659": {
    "x": null,
    "y": null,
    "visible": false,
    "action": "air"
  },
  "957660": {
    "x": 819,
    "y": 804,
    "visible": true,
    "action": "air"
  },
  "957661": {
    "x": 826,
    "y": 798,
    "visible": true,
    "action": "air"
  },
  "957662": {
    "x": 831,
    "y": 791,
    "visible": true,
    "action": "air"
  },
  "957663": {
    "x": 834,
    "y": 787,
    "visible": true,
    "action": "air"
  },
  "957664": {
    "x": 842,
    "y": 776,
    "visible": true,
    "action": "air"
  },
  "957665": {
    "x": 846,
    "y": 767,
    "visible": true,
    "action": "air"
  },
  "957666": {
    "x": 849,
    "y": 759,
    "visible": true,
    "action": "air"
  },
  "957667": {
    "x": 851,
    "y": 745,
    "visible": true,
    "action": "air"
  },
  "957668": {
    "x": 852,
    "y": 732,
    "visible": true,
    "action": "air"
  },
  "957669": {
    "x": 852,
    "y": 724,
    "visible": true,
    "action": "air"
  },
  "957670": {
    "x": 849,
    "y": 710,
    "visible": true,
    "action": "air"
  },
  "957671": {
    "x": 846,
    "y": 696,
    "visible": true,
    "action": "air"
  },
  "957672": {
    "x": 849,
    "y": 684,
    "visible": true,
    "action": "air"
  },
  "957673": {
    "x": 845,
    "y": 670,
    "visible": true,
    "action": "air"
  },
  "957674": {
    "x": 844,
    "y": 657,
    "visible": true,
    "action": "air"
  },
  "957675": {
    "x": 843,
    "y": 647,
    "visible": true,
    "action": "air"
  },
  "957676": {
    "x": 843,
    "y": 636,
    "visible": true,
    "action": "air"
  },
  "957677": {
    "x": 836,
    "y": 626,
    "visible": true,
    "action": "air"
  },
  "957678": {
    "x": 834,
    "y": 617,
    "visible": true,
    "action": "air"
  },
  "957679": {
    "x": 833,
    "y": 608,
    "visible": true,
    "action": "air"
  },
  "957680": {
    "x": 831,
    "y": 598,
    "visible": true,
    "action": "air"
  },
  "957681": {
    "x": 830,
    "y": 592,
    "visible": true,
    "action": "air"
  },
  "957682": {
    "x": 827,
    "y": 583,
    "visible": true,
    "action": "air"
  },
  "957683": {
    "x": 824,
    "y": 576,
    "visible": true,
    "action": "air"
  },
  "957684": {
    "x": 823,
    "y": 569,
    "visible": true,
    "action": "air"
  },
  "957685": {
    "x": 820,
    "y": 563,
    "visible": true,
    "action": "air"
  },
  "957686": {
    "x": 818,
    "y": 557,
    "visible": true,
    "action": "air"
  },
  "957687": {
    "x": 817,
    "y": 552,
    "visible": true,
    "action": "air"
  },
  "957688": {
    "x": 815,
    "y": 547,
    "visible": true,
    "action": "air"
  },
  "957689": {
    "x": 814,
    "y": 543,
    "visible": true,
    "action": "air"
  },
  "957690": {
    "x": 812,
    "y": 537,
    "visible": true,
    "action": "air"
  },
  "957691": {
    "x": 806,
    "y": 534,
    "visible": true,
    "action": "air"
  },
  "957692": {
    "x": 803,
    "y": 530,
    "visible": true,
    "action": "air"
  },
  "957693": {
    "x": 803,
    "y": 528,
    "visible": true,
    "action": "air"
  },
  "957694": {
    "x": 801,
    "y": 525,
    "visible": true,
    "action": "air"
  },
  "957695": {
    "x": 798,
    "y": 522,
    "visible": true,
    "action": "air"
  },
  "957696": {
    "x": 798,
    "y": 522,
    "visible": true,
    "action": "air"
  },
  "957697": {
    "x": 795,
    "y": 521,
    "visible": true,
    "action": "air"
  },
  "957698": {
    "x": 792,
    "y": 520,
    "visible": true,
    "action": "air"
  },
  "957699": {
    "x": 792,
    "y": 519,
    "visible": true,
    "action": "air"
  },
  "957700": {
    "x": null,
    "y": null,
    "visible": false,
    "action": "air"
  },
  "957701": {
    "x": 786,
    "y": 521,
    "visible": true,
    "action": "air"
  },
  "957702": {
    "x": 785,
    "y": 521,
    "visible": true,
    "action": "air"
  },
  "957703": {
    "x": 784,
    "y": 523,
    "visible": true,
    "action": "air"
  },
  "957704": {
    "x": null,
    "y": null,
    "visible": false,
    "action": "air"
  },
  "957705": {
    "x": 775,
    "y": 526,
    "visible": true,
    "action": "air"
  },
  "957706": {
    "x": 775,
    "y": 530,
    "visible": true,
    "action": "air"
  },
  "957707": {
    "x": 773,
    "y": 535,
    "visible": true,
    "action": "air"
  },
  "957708": {
    "x": 772,
    "y": 536,
    "visible": true,
    "action": "air"
  },
  "957709": {
    "x": 770,
    "y": 541,
    "visible": true,
    "action": "air"
  },
  "957710": {
    "x": 767,
    "y": 546,
    "visible": true,
    "action": "air"
  },
  "957711": {
    "x": null,
    "y": null,
    "visible": false,
    "action": "air"
  },
  "957712": {
    "x": 766.7916666666667,
    "y": 547.2083333333335,
    "visible": true,
    "action": "hit"
  },
  "957713": {
    "x": 815,
    "y": 530,
    "visible": true,
    "action": "air"
  },
  "957714": {
    "x": 843,
    "y": 516,
    "visible": true,
    "action": "air"
  },
  "957715": {
    "x": 865,
    "y": 508,
    "visible": true,
    "action": "air"
  },
  "957716": {
    "x": 895,
    "y": 493,
    "visible": true,
    "action": "air"
  },
  "957717": {
    "x": 914,
    "y": 484,
    "visible": true,
    "action": "air"
  },
  "957718": {
    "x": 933,
    "y": 479,
    "visible": true,
    "action": "air"
  },
  "957719": {
    "x": 965,
    "y": 469,
    "visible": true,
    "action": "air"
  },
  "957720": {
    "x": 980,
    "y": 461,
    "visible": true,
    "action": "air"
  },
  "957721": {
    "x": 999,
    "y": 457,
    "visible": true,
    "action": "air"
  },
  "957722": {
    "x": 1015,
    "y": 452,
    "visible": true,
    "action": "air"
  },
  "957723": {
    "x": 1030,
    "y": 446,
    "visible": true,
    "action": "air"
  },
  "957724": {
    "x": 1045,
    "y": 445,
    "visible": true,
    "action": "air"
  },
  "957725": {
    "x": 1063,
    "y": 441,
    "visible": true,
    "action": "air"
  },
  "957726": {
    "x": 1072,
    "y": 438,
    "visible": true,
    "action": "air"
  },
  "957727": {
    "x": 1086,
    "y": 438,
    "visible": true,
    "action": "air"
  },
  "957728": {
    "x": 1099,
    "y": 438,
    "visible": true,
    "action": "air"
  },
  "957729": {
    "x": 1104,
    "y": 436,
    "visible": true,
    "action": "air"
  },
  "957730": {
    "x": 1119,
    "y": 437,
    "visible": true,
    "action": "air"
  },
  "957731": {
    "x": 1129,
    "y": 438,
    "visible": true,
    "action": "air"
  },
  "957732": {
    "x": 1134,
    "y": 438,
    "visible": true,
    "action": "air"
  },
  "957733": {
    "x": 1146,
    "y": 441,
    "visible": true,
    "action": "air"
  },
  "957734": {
    "x": 1153,
    "y": 444,
    "visible": true,
    "action": "air"
  },
  "957735": {
    "x": 1159,
    "y": 447,
    "visible": true,
    "action": "air"
  },
  "957736": {
    "x": 1167,
    "y": 450,
    "visible": true,
    "action": "air"
  },
  "957737": {
    "x": 1177,
    "y": 453,
    "visible": true,
    "action": "air"
  },
  "957738": {
    "x": 1181,
    "y": 456,
    "visible": true,
    "action": "air"
  },
  "957739": {
    "x": 1184.7604166666667,
    "y": 454.76041666666674,
    "visible": true,
    "action": "bounce"
  },
  "957740": {
    "x": 1192,
    "y": 459,
    "visible": true,
    "action": "air"
  },
  "957741": {
    "x": 1196,
    "y": 444,
    "visible": true,
    "action": "air"
  },
  "957742": {
    "x": 1206,
    "y": 429,
    "visible": true,
    "action": "air"
  },
  "957743": {
    "x": 1212,
    "y": 414,
    "visible": true,
    "action": "air"
  },
  "957744": {
    "x": 1218,
    "y": 403,
    "visible": true,
    "action": "air"
  },
  "957745": {
    "x": 1224,
    "y": 391,
    "visible": true,
    "action": "air"
  },
  "957746": {
    "x": 1232,
    "y": 377,
    "visible": true,
    "action": "air"
  },
  "957747": {
    "x": 1238,
    "y": 366,
    "visible": true,
    "action": "air"
  },
  "957748": {
    "x": 1243,
    "y": 355,
    "visible": true,
    "action": "air"
  },
  "957749": {
    "x": 1249,
    "y": 345,
    "visible": true,
    "action": "air"
  },
  "957750": {
    "x": 1254,
    "y": 335,
    "visible": true,
    "action": "air"
  },
  "957751": {
    "x": 1262,
    "y": 326,
    "visible": true,
    "action": "air"
  },
  "957752": {
    "x": 1266,
    "y": 317,
    "visible": true,
    "action": "air"
  },
  "957753": {
    "x": 1270,
    "y": 308,
    "visible": true,
    "action": "air"
  },
  "957754": {
    "x": 1276,
    "y": 299,
    "visible": true,
    "action": "air"
  },
  "957755": {
    "x": 1283,
    "y": 294,
    "visible": true,
    "action": "air"
  },
  "957756": {
    "x": 1285,
    "y": 287,
    "visible": true,
    "action": "air"
  },
  "957757": {
    "x": null,
    "y": null,
    "visible": false,
    "action": "air"
  },
  "957758": {
    "x": 1300,
    "y": 270,
    "visible": true,
    "action": "air"
  },
  "957759": {
    "x": null,
    "y": null,
    "visible": false,
    "action": "air"
  },
  "957760": {
    "x": null,
    "y": null,
    "visible": false,
    "action": "air"
  },
  "957761": {
    "x": null,
    "y": null,
    "visible": false,
    "action": "air"
  },
  "957762": {
    "x": 1311,
    "y": 255,
    "visible": true,
    "action": "air"
  },
  "957763": {
    "x": null,
    "y": null,
    "visible": false,
    "action": "air"
  },
  "957764": {
    "x": null,
    "y": null,
    "visible": false,
    "action": "air"
  },
  "957765": {
    "x": null,
    "y": null,
    "visible": false,
    "action": "air"
  },
  "957766": {
    "x": 1324,
    "y": 243,
    "visible": true,
    "action": "air"
  },
  "957767": {
    "x": 1334,
    "y": 237,
    "visible": true,
    "action": "air"
  },
  "957768": {
    "x": 1333,
    "y": 235,
    "visible": true,
    "action": "air"
  },
  "957769": {
    "x": 1337,
    "y": 234,
    "visible": true,
    "action": "air"
  },
  "957770": {
    "x": 1342,
    "y": 235,
    "visible": true,
    "action": "air"
  },
  "957771": {
    "x": null,
    "y": null,
    "visible": false,
    "action": "air"
  },
  "957772": {
    "x": null,
    "y": null,
    "visible": false,
    "action": "air"
  },
  "957773": {
    "x": null,
    "y": null,
    "visible": false,
    "action": "air"
  },
  "957774": {
    "x": 1346,
    "y": 235,
    "visible": true,
    "action": "air"
  },
  "957775": {
    "x": null,
    "y": null,
    "visible": false,
    "action": "air"
  },
  "957776": {
    "x": null,
    "y": null,
    "visible": false,
    "action": "air"
  },
  "957777": {
    "x": null,
    "y": null,
    "visible": false,
    "action": "air"
  },
  "957778": {
    "x": 1365,
    "y": 234,
    "visible": true,
    "action": "air"
  },
  "957779": {
    "x": 1370,
    "y": 236,
    "visible": true,
    "action": "air"
  },
  "957780": {
    "x": null,
    "y": null,
    "visible": false,
    "action": "air"
  },
  "957781": {
    "x": 1369.6562500000002,
    "y": 232.10416666666674,
    "visible": true,
    "action": "hit"
  },
  "957782": {
    "x": null,
    "y": null,
    "visible": false,
    "action": "air"
  },
  "957783": {
    "x": 1356,
    "y": 235,
    "visible": true,
    "action": "air"
  },
  "957784": {
    "x": 1343,
    "y": 232,
    "visible": true,
    "action": "air"
  },
  "957785": {
    "x": null,
    "y": null,
    "visible": false,
    "action": "air"
  },
  "957786": {
    "x": null,
    "y": null,
    "visible": false,
    "action": "air"
  },
  "957787": {
    "x": null,
    "y": null,
    "visible": false,
    "action": "air"
  },
  "957788": {
    "x": null,
    "y": null,
    "visible": false,
    "action": "air"
  },
  "957789": {
    "x": 1292,
    "y": 233,
    "visible": true,
    "action": "air"
  },
  "957790": {
    "x": 1277,
    "y": 235,
    "visible": true,
    "action": "air"
  },
  "957791": {
    "x": 1266,
    "y": 237,
    "visible": true,
    "action": "air"
  },
  "957792": {
    "x": 1257,
    "y": 238,
    "visible": true,
    "action": "air"
  },
  "957793": {
    "x": 1246,
    "y": 242,
    "visible": true,
    "action": "air"
  },
  "957794": {
    "x": 1235,
    "y": 245,
    "visible": true,
    "action": "air"
  },
  "957795": {
    "x": 1224,
    "y": 248,
    "visible": true,
    "action": "air"
  },
  "957796": {
    "x": 1214,
    "y": 252,
    "visible": true,
    "action": "air"
  },
  "957797": {
    "x": 1197,
    "y": 256,
    "visible": true,
    "action": "air"
  },
  "957798": {
    "x": 1192,
    "y": 262,
    "visible": true,
    "action": "air"
  },
  "957799": {
    "x": 1179,
    "y": 268,
    "visible": true,
    "action": "air"
  },
  "957800": {
    "x": 1164,
    "y": 276,
    "visible": true,
    "action": "air"
  },
  "957801": {
    "x": 1159,
    "y": 278,
    "visible": true,
    "action": "air"
  },
  "957802": {
    "x": 1146,
    "y": 286,
    "visible": true,
    "action": "air"
  },
  "957803": {
    "x": 1133,
    "y": 293,
    "visible": true,
    "action": "air"
  },
  "957804": {
    "x": 1125,
    "y": 298,
    "visible": true,
    "action": "air"
  },
  "957805": {
    "x": 1114,
    "y": 308,
    "visible": true,
    "action": "air"
  },
  "957806": {
    "x": 1099,
    "y": 316,
    "visible": true,
    "action": "air"
  },
  "957807": {
    "x": 1091,
    "y": 325,
    "visible": true,
    "action": "air"
  },
  "957808": {
    "x": 1076,
    "y": 335,
    "visible": true,
    "action": "air"
  },
  "957809": {
    "x": 1065,
    "y": 345,
    "visible": true,
    "action": "air"
  },
  "957810": {
    "x": 1055,
    "y": 355,
    "visible": true,
    "action": "air"
  },
  "957811": {
    "x": 1043,
    "y": 366,
    "visible": true,
    "action": "air"
  },
  "957812": {
    "x": 1029,
    "y": 379,
    "visible": true,
    "action": "air"
  },
  "957813": {
    "x": 1017,
    "y": 389,
    "visible": true,
    "action": "air"
  },
  "957814": {
    "x": 1007,
    "y": 403,
    "visible": true,
    "action": "air"
  },
  "957815": {
    "x": 993,
    "y": 417,
    "visible": true,
    "action": "air"
  },
  "957816": {
    "x": 983,
    "y": 429,
    "visible": true,
    "action": "air"
  },
  "957817": {
    "x": 971,
    "y": 444,
    "visible": true,
    "action": "air"
  },
  "957818": {
    "x": 955,
    "y": 460,
    "visible": true,
    "action": "air"
  },
  "957819": {
    "x": 947,
    "y": 473,
    "visible": true,
    "action": "air"
  },
  "957820": {
    "x": 936,
    "y": 488,
    "visible": true,
    "action": "air"
  },
  "957821": {
    "x": 920,
    "y": 510,
    "visible": true,
    "action": "air"
  },
  "957822": {
    "x": 909,
    "y": 525,
    "visible": true,
    "action": "air"
  },
  "957823": {
    "x": 895,
    "y": 542,
    "visible": true,
    "action": "air"
  },
  "957824": {
    "x": 883,
    "y": 562,
    "visible": true,
    "action": "air"
  },
  "957825": {
    "x": 874,
    "y": 578,
    "visible": true,
    "action": "air"
  },
  "957826": {
    "x": 860,
    "y": 597,
    "visible": true,
    "action": "air"
  },
  "957827": {
    "x": 845,
    "y": 622,
    "visible": true,
    "action": "air"
  },
  "957828": {
    "x": 833,
    "y": 641,
    "visible": true,
    "action": "air"
  },
  "957829": {
    "x": 822,
    "y": 658,
    "visible": true,
    "action": "air"
  },
  "957830": {
    "x": 805,
    "y": 687,
    "visible": true,
    "action": "air"
  },
  "957831": {
    "x": 797,
    "y": 707,
    "visible": true,
    "action": "air"
  },
  "957832": {
    "x": 778.5104166666667,
    "y": 726.8958333333335,
    "visible": true,
    "action": "bounce"
  },
  "957833": {
    "x": 773,
    "y": 725,
    "visible": true,
    "action": "air"
  },
  "957834": {
    "x": 767,
    "y": 718,
    "visible": true,
    "action": "air"
  },
  "957835": {
    "x": 755,
    "y": 715,
    "visible": true,
    "action": "air"
  },
  "957836": {
    "x": 743,
    "y": 710,
    "visible": true,
    "action": "air"
  },
  "957837": {
    "x": 735,
    "y": 707,
    "visible": true,
    "action": "air"
  },
  "957838": {
    "x": 724,
    "y": 704,
    "visible": true,
    "action": "air"
  },
  "957839": {
    "x": 711,
    "y": 701,
    "visible": true,
    "action": "air"
  },
  "957840": {
    "x": 702,
    "y": 698,
    "visible": true,
    "action": "air"
  },
  "957841": {
    "x": 690,
    "y": 697,
    "visible": true,
    "action": "air"
  },
  "957842": {
    "x": 678,
    "y": 697,
    "visible": true,
    "action": "air"
  },
  "957843": {
    "x": 670,
    "y": 695,
    "visible": true,
    "action": "air"
  },
  "957844": {
    "x": 655,
    "y": 695,
    "visible": true,
    "action": "air"
  },
  "957845": {
    "x": 644,
    "y": 695,
    "visible": true,
    "action": "air"
  },
  "957846": {
    "x": 638,
    "y": 694,
    "visible": true,
    "action": "air"
  },
  "957847": {
    "x": 623,
    "y": 698,
    "visible": true,
    "action": "air"
  },
  "957848": {
    "x": 610,
    "y": 699,
    "visible": true,
    "action": "air"
  },
  "957849": {
    "x": 604,
    "y": 701,
    "visible": true,
    "action": "air"
  },
  "957850": {
    "x": 589,
    "y": 705,
    "visible": true,
    "action": "air"
  },
  "957851": {
    "x": 576,
    "y": 708,
    "visible": true,
    "action": "air"
  },
  "957852": {
    "x": 565,
    "y": 712,
    "visible": true,
    "action": "air"
  },
  "957853": {
    "x": 550.6458333333333,
    "y": 711.2708333333335,
    "visible": true,
    "action": "hit"
  },
  "957854": {
    "x": 551,
    "y": 687,
    "visible": true,
    "action": "air"
  },
  "957855": {
    "x": 558,
    "y": 654,
    "visible": true,
    "action": "air"
  },
  "957856": {
    "x": 564,
    "y": 624,
    "visible": true,
    "action": "air"
  },
  "957857": {
    "x": 566,
    "y": 593,
    "visible": true,
    "action": "air"
  },
  "957858": {
    "x": 573,
    "y": 568,
    "visible": true,
    "action": "air"
  },
  "957859": {
    "x": 578,
    "y": 547,
    "visible": true,
    "action": "air"
  },
  "957860": {
    "x": 579,
    "y": 527,
    "visible": true,
    "action": "air"
  },
  "957861": {
    "x": 579,
    "y": 515,
    "visible": true,
    "action": "air"
  },
  "957862": {
    "x": 589,
    "y": 487,
    "visible": true,
    "action": "air"
  },
  "957863": {
    "x": 594,
    "y": 462,
    "visible": true,
    "action": "air"
  },
  "957864": {
    "x": 595,
    "y": 451,
    "visible": true,
    "action": "air"
  },
  "957865": {
    "x": 604,
    "y": 436,
    "visible": true,
    "action": "air"
  },
  "957866": {
    "x": 606,
    "y": 423,
    "visible": true,
    "action": "air"
  },
  "957867": {
    "x": 609,
    "y": 412,
    "visible": true,
    "action": "air"
  },
  "957868": {
    "x": 612,
    "y": 401,
    "visible": true,
    "action": "air"
  },
  "957869": {
    "x": 616,
    "y": 393,
    "visible": true,
    "action": "air"
  },
  "957870": {
    "x": 619,
    "y": 382,
    "visible": true,
    "action": "air"
  },
  "957871": {
    "x": 621,
    "y": 375,
    "visible": true,
    "action": "air"
  },
  "957872": {
    "x": 624,
    "y": 366,
    "visible": true,
    "action": "air"
  },
  "957873": {
    "x": 624,
    "y": 361,
    "visible": true,
    "action": "air"
  },
  "957874": {
    "x": 632,
    "y": 355,
    "visible": true,
    "action": "air"
  },
  "957875": {
    "x": 634,
    "y": 349,
    "visible": true,
    "action": "air"
  },
  "957876": {
    "x": 635,
    "y": 346,
    "visible": true,
    "action": "air"
  },
  "957877": {
    "x": 638,
    "y": 343,
    "visible": true,
    "action": "air"
  },
  "957878": {
    "x": 642,
    "y": 339,
    "visible": true,
    "action": "air"
  },
  "957879": {
    "x": 641,
    "y": 335,
    "visible": true,
    "action": "air"
  },
  "957880": {
    "x": 644,
    "y": 334,
    "visible": true,
    "action": "air"
  },
  "957881": {
    "x": null,
    "y": null,
    "visible": false,
    "action": "air"
  },
  "957882": {
    "x": 649,
    "y": 332,
    "visible": true,
    "action": "air"
  },
  "957883": {
    "x": 651,
    "y": 332,
    "visible": true,
    "action": "air"
  },
  "957884": {
    "x": null,
    "y": null,
    "visible": false,
    "action": "air"
  },
  "957885": {
    "x": null,
    "y": null,
    "visible": false,
    "action": "air"
  },
  "957886": {
    "x": 656,
    "y": 333,
    "visible": true,
    "action": "air"
  },
  "957887": {
    "x": 664,
    "y": 335,
    "visible": true,
    "action": "air"
  },
  "957888": {
    "x": 664,
    "y": 335,
    "visible": true,
    "action": "air"
  },
  "957889": {
    "x": 666,
    "y": 337,
    "visible": true,
    "action": "air"
  },
  "957890": {
    "x": 668,
    "y": 341,
    "visible": true,
    "action": "air"
  },
  "957891": {
    "x": 669,
    "y": 342,
    "visible": true,
    "action": "air"
  },
  "957892": {
    "x": 670,
    "y": 344,
    "visible": true,
    "action": "air"
  },
  "957893": {
    "x": 669.1354166666665,
    "y": 340.1770833333335,
    "visible": true,
    "action": "bounce"
  },
  "957894": {
    "x": 673,
    "y": 343,
    "visible": true,
    "action": "air"
  },
  "957895": {
    "x": 676,
    "y": 334,
    "visible": true,
    "action": "air"
  },
  "957896": {
    "x": 676,
    "y": 321,
    "visible": true,
    "action": "air"
  },
  "957897": {
    "x": 676,
    "y": 311,
    "visible": true,
    "action": "air"
  },
  "957898": {
    "x": 678,
    "y": 302,
    "visible": true,
    "action": "air"
  },
  "957899": {
    "x": 679,
    "y": 292,
    "visible": true,
    "action": "air"
  },
  "957900": {
    "x": 679,
    "y": 284,
    "visible": true,
    "action": "air"
  },
  "957901": {
    "x": 680,
    "y": 278,
    "visible": true,
    "action": "air"
  },
  "957902": {
    "x": 681,
    "y": 269,
    "visible": true,
    "action": "air"
  },
  "957903": {
    "x": 682,
    "y": 261,
    "visible": true,
    "action": "air"
  },
  "957904": {
    "x": 682,
    "y": 254,
    "visible": true,
    "action": "air"
  },
  "957905": {
    "x": 683,
    "y": 246,
    "visible": true,
    "action": "air"
  },
  "957906": {
    "x": 683,
    "y": 242,
    "visible": true,
    "action": "air"
  },
  "957907": {
    "x": 685,
    "y": 236,
    "visible": true,
    "action": "air"
  },
  "957908": {
    "x": 685,
    "y": 230,
    "visible": true,
    "action": "air"
  },
  "957909": {
    "x": 685,
    "y": 226,
    "visible": true,
    "action": "air"
  },
  "957910": {
    "x": 688,
    "y": 220,
    "visible": true,
    "action": "air"
  },
  "957911": {
    "x": 690,
    "y": 214,
    "visible": true,
    "action": "air"
  },
  "957912": {
    "x": 688,
    "y": 212,
    "visible": true,
    "action": "air"
  },
  "957913": {
    "x": 692,
    "y": 208,
    "visible": true,
    "action": "air"
  },
  "957914": {
    "x": 693,
    "y": 204,
    "visible": true,
    "action": "air"
  },
  "957915": {
    "x": 1705,
    "y": 534,
    "visible": true,
    "action": "air"
  },
  "957916": {
    "x": 1701,
    "y": 527,
    "visible": true,
    "action": "air"
  },
  "957917": {
    "x": 1700,
    "y": 520,
    "visible": true,
    "action": "air"
  },
  "957918": {
    "x": 1700,
    "y": 515,
    "visible": true,
    "action": "air"
  },
  "957919": {
    "x": null,
    "y": null,
    "visible": false,
    "action": "air"
  },
  "957920": {
    "x": 1702,
    "y": 506,
    "visible": true,
    "action": "air"
  },
  "957921": {
    "x": null,
    "y": null,
    "visible": false,
    "action": "air"
  },
  "957922": {
    "x": null,
    "y": null,
    "visible": false,
    "action": "air"
  },
  "957923": {
    "x": null,
    "y": null,
    "visible": false,
    "action": "air"
  },
  "957924": {
    "x": null,
    "y": null,
    "visible": false,
    "action": "air"
  },
  "957925": {
    "x": null,
    "y": null,
    "visible": false,
    "action": "air"
  },
  "957926": {
    "x": null,
    "y": null,
    "visible": false,
    "action": "air"
  },
  "957927": {
    "x": null,
    "y": null,
    "visible": false,
    "action": "air"
  },
  "957928": {
    "x": null,
    "y": null,
    "visible": false,
    "action": "air"
  },
  "957929": {
    "x": null,
    "y": null,
    "visible": false,
    "action": "air"
  },
  "957930": {
    "x": null,
    "y": null,
    "visible": false,
    "action": "air"
  },
  "957931": {
    "x": null,
    "y": null,
    "visible": false,
    "action": "air"
  },
  "957932": {
    "x": null,
    "y": null,
    "visible": false,
    "action": "air"
  },
  "957933": {
    "x": null,
    "y": null,
    "visible": false,
    "action": "air"
  },
  "957934": {
    "x": null,
    "y": null,
    "visible": false,
    "action": "air"
  },
  "957935": {
    "x": null,
    "y": null,
    "visible": false,
    "action": "air"
  },
  "957936": {
    "x": null,
    "y": null,
    "visible": false,
    "action": "air"
  },
  "957937": {
    "x": null,
    "y": null,
    "visible": false,
    "action": "air"
  },
  "957938": {
    "x": null,
    "y": null,
    "visible": false,
    "action": "air"
  },
  "957939": {
    "x": null,
    "y": null,
    "visible": false,
    "action": "air"
  },
  "957940": {
    "x": null,
    "y": null,
    "visible": false,
    "action": "air"
  },
  "957941": {
    "x": null,
    "y": null,
    "visible": false,
    "action": "air"
  },
  "957942": {
    "x": null,
    "y": null,
    "visible": false,
    "action": "air"
  },
  "957943": {
    "x": null,
    "y": null,
    "visible": false,
    "action": "air"
  },
  "957944": {
    "x": null,
    "y": null,
    "visible": false,
    "action": "air"
  },
  "957945": {
    "x": null,
    "y": null,
    "visible": false,
    "action": "air"
  },
  "957946": {
    "x": null,
    "y": null,
    "visible": false,
    "action": "air"
  },
  "957947": {
    "x": null,
    "y": null,
    "visible": false,
    "action": "air"
  },
  "957948": {
    "x": null,
    "y": null,
    "visible": false,
    "action": "air"
  },
  "957949": {
    "x": null,
    "y": null,
    "visible": false,
    "action": "air"
  },
  "957950": {
    "x": null,
    "y": null,
    "visible": false,
    "action": "air"
  },
  "957951": {
    "x": null,
    "y": null,
    "visible": false,
    "action": "air"
  },
  "957952": {
    "x": null,
    "y": null,
    "visible": false,
    "action": "air"
  },
  "957953": {
    "x": 656,
    "y": 203,
    "visible": true,
    "action": "air"
  },
  "957954": {
    "x": 654,
    "y": 204,
    "visible": true,
    "action": "air"
  },
  "957955": {
    "x": 654,
    "y": 208,
    "visible": true,
    "action": "air"
  },
  "957956": {
    "x": 652,
    "y": 212,
    "visible": true,
    "action": "air"
  },
  "957957": {
    "x": 650,
    "y": 214,
    "visible": true,
    "action": "air"
  },
  "957958": {
    "x": 648,
    "y": 220,
    "visible": true,
    "action": "air"
  },
  "957959": {
    "x": 647,
    "y": 226,
    "visible": true,
    "action": "air"
  },
  "957960": {
    "x": 645,
    "y": 229,
    "visible": true,
    "action": "air"
  },
  "957961": {
    "x": 644,
    "y": 234,
    "visible": true,
    "action": "air"
  },
  "957962": {
    "x": 641,
    "y": 238,
    "visible": true,
    "action": "air"
  },
  "957963": {
    "x": 639,
    "y": 244,
    "visible": true,
    "action": "air"
  },
  "957964": {
    "x": 639,
    "y": 250,
    "visible": true,
    "action": "air"
  },
  "957965": {
    "x": 637,
    "y": 256,
    "visible": true,
    "action": "air"
  },
  "957966": {
    "x": 635,
    "y": 262,
    "visible": true,
    "action": "air"
  },
  "957967": {
    "x": 633,
    "y": 268,
    "visible": true,
    "action": "air"
  },
  "957968": {
    "x": 633,
    "y": 275,
    "visible": true,
    "action": "air"
  },
  "957969": {
    "x": 630,
    "y": 280,
    "visible": true,
    "action": "air"
  },
  "957970": {
    "x": 626,
    "y": 287,
    "visible": true,
    "action": "air"
  },
  "957971": {
    "x": 626,
    "y": 295,
    "visible": true,
    "action": "air"
  },
  "957972": {
    "x": 625,
    "y": 299,
    "visible": true,
    "action": "air"
  },
  "957973": {
    "x": 623,
    "y": 309,
    "visible": true,
    "action": "air"
  },
  "957974": {
    "x": 622,
    "y": 316,
    "visible": true,
    "action": "air"
  },
  "957975": {
    "x": 620,
    "y": 323,
    "visible": true,
    "action": "air"
  },
  "957976": {
    "x": 619,
    "y": 324,
    "visible": true,
    "action": "air"
  },
  "957977": {
    "x": 615,
    "y": 318,
    "visible": true,
    "action": "air"
  },
  "957978": {
    "x": 617,
    "y": 315,
    "visible": true,
    "action": "air"
  },
  "957979": {
    "x": 616,
    "y": 311,
    "visible": true,
    "action": "air"
  },
  "957980": {
    "x": 615,
    "y": 306,
    "visible": true,
    "action": "air"
  },
  "957981": {
    "x": 613,
    "y": 302,
    "visible": true,
    "action": "air"
  },
  "957982": {
    "x": 614,
    "y": 298,
    "visible": true,
    "action": "air"
  },
  "957983": {
    "x": 612,
    "y": 295,
    "visible": true,
    "action": "air"
  },
  "957984": {
    "x": null,
    "y": null,
    "visible": false,
    "action": "air"
  },
  "957985": {
    "x": null,
    "y": null,
    "visible": false,
    "action": "air"
  },
  "957986": {
    "x": null,
    "y": null,
    "visible": false,
    "action": "air"
  },
  "957987": {
    "x": 610,
    "y": 285,
    "visible": true,
    "action": "air"
  },
  "957988": {
    "x": 610,
    "y": 283,
    "visible": true,
    "action": "air"
  },
  "957989": {
    "x": 607,
    "y": 280,
    "visible": true,
    "action": "air"
  },
  "957990": {
    "x": null,
    "y": null,
    "visible": false,
    "action": "air"
  },
  "957991": {
    "x": null,
    "y": null,
    "visible": false,
    "action": "air"
  },
  "957992": {
    "x": null,
    "y": null,
    "visible": false,
    "action": "air"
  },
  "957993": {
    "x": null,
    "y": null,
    "visible": false,
    "action": "air"
  },
  "957994": {
    "x": null,
    "y": null,
    "visible": false,
    "action": "air"
  },
  "957995": {
    "x": null,
    "y": null,
    "visible": false,
    "action": "air"
  },
  "957996": {
    "x": null,
    "y": null,
    "visible": false,
    "action": "air"
  }
}