{
  "442248": {
    "x": null,
    "y": null,
    "visible": false,
    "action": "air"
  },
  "442249": {
    "x": null,
    "y": null,
    "visible": false,
    "action": "air"
  },
  "442250": {
    "x": null,
    "y": null,
    "visible": false,
    "action": "air"
  },
  "442251": {
    "x": null,
    "y": null,
    "visible": false,
    "action": "air"
  },
  "442252": {
    "x": null,
    "y": null,
    "visible": false,
    "action": "air"
  },
  "442253": {
    "x": null,
    "y": null,
    "visible": false,
    "action": "air"
  },
  "442254": {
    "x": null,
    "y": null,
    "visible": false,
    "action": "air"
  },
  "442255": {
    "x": null,
    "y": null,
    "visible": false,
    "action": "air"
  },
  "442256": {
    "x": null,
    "y": null,
    "visible": false,
    "action": "air"
  },
  "442257": {
    "x": null,
    "y": null,
    "visible": false,
    "action": "air"
  },
  "442258": {
    "x": null,
    "y": null,
    "visible": false,
    "action": "air"
  },
  "442259": {
    "x": null,
    "y": null,
    "visible": false,
    "action": "air"
  },
  "442260": {
    "x": null,
    "y": null,
    "visible": false,
    "action": "air"
  },
  "442261": {
    "x": null,
    "y": null,
    "visible": false,
    "action": "air"
  },
  "442262": {
    "x": null,
    "y": null,
    "visible": false,
    "action": "air"
  },
  "442263": {
    "x": null,
    "y": null,
    "visible": false,
    "action": "air"
  },
  "442264": {
    "x": null,
    "y": null,
    "visible": false,
    "action": "air"
  },
  "442265": {
    "x": null,
    "y": null,
    "visible": false,
    "action": "air"
  },
  "442266": {
    "x": null,
    "y": null,
    "visible": false,
    "action": "air"
  },
  "442267": {
    "x": null,
    "y": null,
    "visible": false,
    "action": "air"
  },
  "442268": {
    "x": null,
    "y": null,
    "visible": false,
    "action": "air"
  },
  "442269": {
    "x": null,
    "y": null,
    "visible": false,
    "action": "air"
  },
  "442270": {
    "x": null,
    "y": null,
    "visible": false,
    "action": "air"
  },
  "442271": {
    "x": null,
    "y": null,
    "visible": false,
    "action": "air"
  },
  "442272": {
    "x": null,
    "y": null,
    "visible": false,
    "action": "air"
  },
  "442273": {
    "x": null,
    "y": null,
    "visible": false,
    "action": "air"
  },
  "442274": {
    "x": null,
    "y": null,
    "visible": false,
    "action": "air"
  },
  "442275": {
    "x": null,
    "y": null,
    "visible": false,
    "action": "air"
  },
  "442276": {
    "x": null,
    "y": null,
    "visible": false,
    "action": "air"
  },
  "442277": {
    "x": null,
    "y": null,
    "visible": false,
    "action": "air"
  },
  "442278": {
    "x": null,
    "y": null,
    "visible": false,
    "action": "air"
  },
  "442279": {
    "x": null,
    "y": null,
    "visible": false,
    "action": "air"
  },
  "442280": {
    "x": null,
    "y": null,
    "visible": false,
    "action": "air"
  },
  "442281": {
    "x": null,
    "y": null,
    "visible": false,
    "action": "air"
  },
  "442282": {
    "x": null,
    "y": null,
    "visible": false,
    "action": "air"
  },
  "442283": {
    "x": null,
    "y": null,
    "visible": false,
    "action": "air"
  },
  "442284": {
    "x": null,
    "y": null,
    "visible": false,
    "action": "air"
  },
  "442285": {
    "x": null,
    "y": null,
    "visible": false,
    "action": "air"
  },
  "442286": {
    "x": null,
    "y": null,
    "visible": false,
    "action": "air"
  },
  "442287": {
    "x": null,
    "y": null,
    "visible": false,
    "action": "air"
  },
  "442288": {
    "x": null,
    "y": null,
    "visible": false,
    "action": "air"
  },
  "442289": {
    "x": null,
    "y": null,
    "visible": false,
    "action": "air"
  },
  "442290": {
    "x": null,
    "y": null,
    "visible": false,
    "action": "air"
  },
  "442291": {
    "x": null,
    "y": null,
    "visible": false,
    "action": "air"
  },
  "442292": {
    "x": null,
    "y": null,
    "visible": false,
    "action": "air"
  },
  "442293": {
    "x": null,
    "y": null,
    "visible": false,
    "action": "air"
  },
  "442294": {
    "x": null,
    "y": null,
    "visible": false,
    "action": "air"
  },
  "442295": {
    "x": null,
    "y": null,
    "visible": false,
    "action": "air"
  },
  "442296": {
    "x": null,
    "y": null,
    "visible": false,
    "action": "air"
  },
  "442297": {
    "x": null,
    "y": null,
    "visible": false,
    "action": "air"
  },
  "442298": {
    "x": null,
    "y": null,
    "visible": false,
    "action": "air"
  },
  "442299": {
    "x": null,
    "y": null,
    "visible": false,
    "action": "air"
  },
  "442300": {
    "x": null,
    "y": null,
    "visible": false,
    "action": "air"
  },
  "442301": {
    "x": null,
    "y": null,
    "visible": false,
    "action": "air"
  },
  "442302": {
    "x": null,
    "y": null,
    "visible": false,
    "action": "air"
  },
  "442303": {
    "x": null,
    "y": null,
    "visible": false,
    "action": "air"
  },
  "442304": {
    "x": null,
    "y": null,
    "visible": false,
    "action": "air"
  },
  "442305": {
    "x": null,
    "y": null,
    "visible": false,
    "action": "air"
  },
  "442306": {
    "x": null,
    "y": null,
    "visible": false,
    "action": "air"
  },
  "442307": {
    "x": null,
    "y": null,
    "visible": false,
    "action": "air"
  },
  "442308": {
    "x": null,
    "y": null,
    "visible": false,
    "action": "air"
  },
  "442309": {
    "x": null,
    "y": null,
    "visible": false,
    "action": "air"
  },
  "442310": {
    "x": null,
    "y": null,
    "visible": false,
    "action": "air"
  },
  "442311": {
    "x": null,
    "y": null,
    "visible": false,
    "action": "air"
  },
  "442312": {
    "x": null,
    "y": null,
    "visible": false,
    "action": "air"
  },
  "442313": {
    "x": null,
    "y": null,
    "visible": false,
    "action": "air"
  },
  "442314": {
    "x": null,
    "y": null,
    "visible": false,
    "action": "air"
  },
  "442315": {
    "x": null,
    "y": null,
    "visible": false,
    "action": "air"
  },
  "442316": {
    "x": null,
    "y": null,
    "visible": false,
    "action": "air"
  },
  "442317": {
    "x": null,
    "y": null,
    "visible": false,
    "action": "air"
  },
  "442318": {
    "x": null,
    "y": null,
    "visible": false,
    "action": "air"
  },
  "442319": {
    "x": null,
    "y": null,
    "visible": false,
    "action": "air"
  },
  "442320": {
    "x": null,
    "y": null,
    "visible": false,
    "action": "air"
  },
  "442321": {
    "x": null,
    "y": null,
    "visible": false,
    "action": "air"
  },
  "442322": {
    "x": null,
    "y": null,
    "visible": false,
    "action": "air"
  },
  "442323": {
    "x": null,
    "y": null,
    "visible": false,
    "action": "air"
  },
  "442324": {
    "x": null,
    "y": null,
    "visible": false,
    "action": "air"
  },
  "442325": {
    "x": null,
    "y": null,
    "visible": false,
    "action": "air"
  },
  "442326": {
    "x": null,
    "y": null,
    "visible": false,
    "action": "air"
  },
  "442327": {
    "x": null,
    "y": null,
    "visible": false,
    "action": "air"
  },
  "442328": {
    "x": null,
    "y": null,
    "visible": false,
    "action": "air"
  },
  "442329": {
    "x": null,
    "y": null,
    "visible": false,
    "action": "air"
  },
  "442330": {
    "x": null,
    "y": null,
    "visible": false,
    "action": "air"
  },
  "442331": {
    "x": null,
    "y": null,
    "visible": false,
    "action": "air"
  },
  "442332": {
    "x": null,
    "y": null,
    "visible": false,
    "action": "air"
  },
  "442333": {
    "x": null,
    "y": null,
    "visible": false,
    "action": "air"
  },
  "442334": {
    "x": null,
    "y": null,
    "visible": false,
    "action": "air"
  },
  "442335": {
    "x": null,
    "y": null,
    "visible": false,
    "action": "air"
  },
  "442336": {
    "x": null,
    "y": null,
    "visible": false,
    "action": "air"
  },
  "442337": {
    "x": null,
    "y": null,
    "visible": false,
    "action": "air"
  },
  "442338": {
    "x": null,
    "y": null,
    "visible": false,
    "action": "air"
  },
  "442339": {
    "x": null,
    "y": null,
    "visible": false,
    "action": "air"
  },
  "442340": {
    "x": null,
    "y": null,
    "visible": false,
    "action": "air"
  },
  "442341": {
    "x": null,
    "y": null,
    "visible": false,
    "action": "air"
  },
  "442342": {
    "x": null,
    "y": null,
    "visible": false,
    "action": "air"
  },
  "442343": {
    "x": null,
    "y": null,
    "visible": false,
    "action": "air"
  },
  "442344": {
    "x": null,
    "y": null,
    "visible": false,
    "action": "air"
  },
  "442345": {
    "x": null,
    "y": null,
    "visible": false,
    "action": "air"
  },
  "442346": {
    "x": null,
    "y": null,
    "visible": false,
    "action": "air"
  },
  "442347": {
    "x": null,
    "y": null,
    "visible": false,
    "action": "air"
  },
  "442348": {
    "x": null,
    "y": null,
    "visible": false,
    "action": "air"
  },
  "442349": {
    "x": null,
    "y": null,
    "visible": false,
    "action": "air"
  },
  "442350": {
    "x": null,
    "y": null,
    "visible": false,
    "action": "air"
  },
  "442351": {
    "x": null,
    "y": null,
    "visible": false,
    "action": "air"
  },
  "442352": {
    "x": null,
    "y": null,
    "visible": false,
    "action": "air"
  },
  "442353": {
    "x": null,
    "y": null,
    "visible": false,
    "action": "air"
  },
  "442354": {
    "x": null,
    "y": null,
    "visible": false,
    "action": "air"
  },
  "442355": {
    "x": null,
    "y": null,
    "visible": false,
    "action": "air"
  },
  "442356": {
    "x": null,
    "y": null,
    "visible": false,
    "action": "air"
  },
  "442357": {
    "x": null,
    "y": null,
    "visible": false,
    "action": "air"
  },
  "442358": {
    "x": null,
    "y": null,
    "visible": false,
    "action": "air"
  },
  "442359": {
    "x": null,
    "y": null,
    "visible": false,
    "action": "air"
  },
  "442360": {
    "x": null,
    "y": null,
    "visible": false,
    "action": "air"
  },
  "442361": {
    "x": null,
    "y": null,
    "visible": false,
    "action": "air"
  },
  "442362": {
    "x": null,
    "y": null,
    "visible": false,
    "action": "air"
  },
  "442363": {
    "x": null,
    "y": null,
    "visible": false,
    "action": "air"
  },
  "442364": {
    "x": null,
    "y": null,
    "visible": false,
    "action": "air"
  },
  "442365": {
    "x": 829,
    "y": 242,
    "visible": true,
    "action": "air"
  },
  "442366": {
    "x": 831,
    "y": 236,
    "visible": true,
    "action": "air"
  },
  "442367": {
    "x": 830,
    "y": 227,
    "visible": true,
    "action": "air"
  },
  "442368": {
    "x": 830,
    "y": 220,
    "visible": true,
    "action": "air"
  },
  "442369": {
    "x": 830,
    "y": 214,
    "visible": true,
    "action": "air"
  },
  "442370": {
    "x": 832,
    "y": 207,
    "visible": true,
    "action": "air"
  },
  "442371": {
    "x": 832,
    "y": 202,
    "visible": true,
    "action": "air"
  },
  "442372": {
    "x": 831,
    "y": 195,
    "visible": true,
    "action": "air"
  },
  "442373": {
    "x": 832,
    "y": 189,
    "visible": true,
    "action": "air"
  },
  "442374": {
    "x": 831,
    "y": 184,
    "visible": true,
    "action": "air"
  },
  "442375": {
    "x": 831,
    "y": 181,
    "visible": true,
    "action": "air"
  },
  "442376": {
    "x": 833,
    "y": 176,
    "visible": true,
    "action": "air"
  },
  "442377": {
    "x": null,
    "y": null,
    "visible": false,
    "action": "air"
  },
  "442378": {
    "x": null,
    "y": null,
    "visible": false,
    "action": "air"
  },
  "442379": {
    "x": null,
    "y": null,
    "visible": false,
    "action": "air"
  },
  "442380": {
    "x": null,
    "y": null,
    "visible": false,
    "action": "air"
  },
  "442381": {
    "x": null,
    "y": null,
    "visible": false,
    "action": "air"
  },
  "442382": {
    "x": null,
    "y": null,
    "visible": false,
    "action": "air"
  },
  "442383": {
    "x": null,
    "y": null,
    "visible": false,
    "action": "air"
  },
  "442384": {
    "x": null,
    "y": null,
    "visible": false,
    "action": "air"
  },
  "442385": {
    "x": null,
    "y": null,
    "visible": false,
    "action": "air"
  },
  "442386": {
    "x": null,
    "y": null,
    "visible": false,
    "action": "air"
  },
  "442387": {
    "x": null,
    "y": null,
    "visible": false,
    "action": "air"
  },
  "442388": {
    "x": null,
    "y": null,
    "visible": false,
    "action": "air"
  },
  "442389": {
    "x": null,
    "y": null,
    "visible": false,
    "action": "air"
  },
  "442390": {
    "x": null,
    "y": null,
    "visible": false,
    "action": "air"
  },
  "442391": {
    "x": null,
    "y": null,
    "visible": false,
    "action": "air"
  },
  "442392": {
    "x": null,
    "y": null,
    "visible": false,
    "action": "air"
  },
  "442393": {
    "x": null,
    "y": null,
    "visible": false,
    "action": "air"
  },
  "442394": {
    "x": null,
    "y": null,
    "visible": false,
    "action": "air"
  },
  "442395": {
    "x": null,
    "y": null,
    "visible": false,
    "action": "air"
  },
  "442396": {
    "x": null,
    "y": null,
    "visible": false,
    "action": "air"
  },
  "442397": {
    "x": null,
    "y": null,
    "visible": false,
    "action": "air"
  },
  "442398": {
    "x": null,
    "y": null,
    "visible": false,
    "action": "air"
  },
  "442399": {
    "x": null,
    "y": null,
    "visible": false,
    "action": "air"
  },
  "442400": {
    "x": null,
    "y": null,
    "visible": false,
    "action": "air"
  },
  "442401": {
    "x": 835,
    "y": 132,
    "visible": true,
    "action": "air"
  },
  "442402": {
    "x": 836,
    "y": 136,
    "visible": true,
    "action": "air"
  },
  "442403": {
    "x": 842,
    "y": 138,
    "visible": true,
    "action": "air"
  },
  "442404": {
    "x": 842,
    "y": 140,
    "visible": true,
    "action": "air"
  },
  "442405": {
    "x": 836,
    "y": 142,
    "visible": true,
    "action": "air"
  },
  "442406": {
    "x": null,
    "y": null,
    "visible": false,
    "action": "air"
  },
  "442407": {
    "x": 842,
    "y": 145,
    "visible": true,
    "action": "air"
  },
  "442408": {
    "x": 838,
    "y": 148,
    "visible": true,
    "action": "air"
  },
  "442409": {
    "x": null,
    "y": null,
    "visible": false,
    "action": "air"
  },
  "442410": {
    "x": 836,
    "y": 156,
    "visible": true,
    "action": "air"
  },
  "442411": {
    "x": 843,
    "y": 159,
    "visible": true,
    "action": "air"
  },
  "442412": {
    "x": 837,
    "y": 163,
    "visible": true,
    "action": "air"
  },
  "442413": {
    "x": null,
    "y": null,
    "visible": false,
    "action": "air"
  },
  "442414": {
    "x": null,
    "y": null,
    "visible": false,
    "action": "air"
  },
  "442415": {
    "x": 836.179841897233,
    "y": 171.792490118577,
    "visible": true,
    "action": "hit"
  },
  "442416": {
    "x": 853,
    "y": 202,
    "visible": true,
    "action": "air"
  },
  "442417": {
    "x": null,
    "y": null,
    "visible": false,
    "action": "air"
  },
  "442418": {
    "x": null,
    "y": null,
    "visible": false,
    "action": "air"
  },
  "442419": {
    "x": null,
    "y": null,
    "visible": false,
    "action": "air"
  },
  "442420": {
    "x": null,
    "y": null,
    "visible": false,
    "action": "air"
  },
  "442421": {
    "x": null,
    "y": null,
    "visible": false,
    "action": "air"
  },
  "442422": {
    "x": 908,
    "y": 340,
    "visible": true,
    "action": "air"
  },
  "442423": {
    "x": 922,
    "y": 369,
    "visible": true,
    "action": "air"
  },
  "442424": {
    "x": 937,
    "y": 397,
    "visible": true,
    "action": "air"
  },
  "442425": {
    "x": 939,
    "y": 418,
    "visible": true,
    "action": "air"
  },
  "442426": {
    "x": 955,
    "y": 454,
    "visible": true,
    "action": "air"
  },
  "442427": {
    "x": 964,
    "y": 473,
    "visible": true,
    "action": "air"
  },
  "442428": {
    "x": 977,
    "y": 513,
    "visible": true,
    "action": "air"
  },
  "442429": {
    "x": 986,
    "y": 538,
    "visible": true,
    "action": "air"
  },
  "442430": {
    "x": 1002,
    "y": 579,
    "visible": true,
    "action": "air"
  },
  "442431": {
    "x": 1011,
    "y": 608,
    "visible": true,
    "action": "air"
  },
  "442432": {
    "x": 1016.4169960474305,
    "y": 627.1284584980237,
    "visible": true,
    "action": "bounce"
  },
  "442433": {
    "x": 1032,
    "y": 638,
    "visible": true,
    "action": "air"
  },
  "442434": {
    "x": 1039,
    "y": 641,
    "visible": true,
    "action": "air"
  },
  "442435": {
    "x": 1053,
    "y": 645,
    "visible": true,
    "action": "air"
  },
  "442436": {
    "x": 1063,
    "y": 650,
    "visible": true,
    "action": "air"
  },
  "442437": {
    "x": 1070,
    "y": 653,
    "visible": true,
    "action": "air"
  },
  "442438": {
    "x": 1082,
    "y": 659,
    "visible": true,
    "action": "air"
  },
  "442439": {
    "x": 1093,
    "y": 668,
    "visible": true,
    "action": "air"
  },
  "442440": {
    "x": 1102,
    "y": 674,
    "visible": true,
    "action": "air"
  },
  "442441": {
    "x": 1116,
    "y": 683,
    "visible": true,
    "action": "air"
  },
  "442442": {
    "x": 1128,
    "y": 694,
    "visible": true,
    "action": "air"
  },
  "442443": {
    "x": 1135,
    "y": 702,
    "visible": true,
    "action": "air"
  },
  "442444": {
    "x": 1150,
    "y": 714,
    "visible": true,
    "action": "air"
  },
  "442445": {
    "x": 1165,
    "y": 730,
    "visible": true,
    "action": "air"
  },
  "442446": {
    "x": 1175,
    "y": 740,
    "visible": true,
    "action": "air"
  },
  "442447": {
    "x": 1189,
    "y": 755,
    "visible": true,
    "action": "air"
  },
  "442448": {
    "x": 1199.0256916996045,
    "y": 762.3063241106722,
    "visible": true,
    "action": "hit"
  },
  "442449": {
    "x": 1186,
    "y": 733,
    "visible": true,
    "action": "air"
  },
  "442450": {
    "x": 1176,
    "y": 704,
    "visible": true,
    "action": "air"
  },
  "442451": {
    "x": 1160,
    "y": 674,
    "visible": true,
    "action": "air"
  },
  "442452": {
    "x": 1148,
    "y": 647,
    "visible": true,
    "action": "air"
  },
  "442453": {
    "x": 1137,
    "y": 626,
    "visible": true,
    "action": "air"
  },
  "442454": {
    "x": 1127,
    "y": 599,
    "visible": true,
    "action": "air"
  },
  "442455": {
    "x": 1120,
    "y": 580,
    "visible": true,
    "action": "air"
  },
  "442456": {
    "x": 1107,
    "y": 561,
    "visible": true,
    "action": "air"
  },
  "442457": {
    "x": 1098,
    "y": 539,
    "visible": true,
    "action": "air"
  },
  "442458": {
    "x": 1090,
    "y": 524,
    "visible": true,
    "action": "air"
  },
  "442459": {
    "x": 1084,
    "y": 508,
    "visible": true,
    "action": "air"
  },
  "442460": {
    "x": 1072,
    "y": 492,
    "visible": true,
    "action": "air"
  },
  "442461": {
    "x": 1066,
    "y": 477,
    "visible": true,
    "action": "air"
  },
  "442462": {
    "x": 1058,
    "y": 465,
    "visible": true,
    "action": "air"
  },
  "442463": {
    "x": 1049,
    "y": 451,
    "visible": true,
    "action": "air"
  },
  "442464": {
    "x": 1044,
    "y": 441,
    "visible": true,
    "action": "air"
  },
  "442465": {
    "x": 1037,
    "y": 431,
    "visible": true,
    "action": "air"
  },
  "442466": {
    "x": 1029,
    "y": 418,
    "visible": true,
    "action": "air"
  },
  "442467": {
    "x": 1025,
    "y": 410,
    "visible": true,
    "action": "air"
  },
  "442468": {
    "x": 1016,
    "y": 401,
    "visible": true,
    "action": "air"
  },
  "442469": {
    "x": 1011,
    "y": 394,
    "visible": true,
    "action": "air"
  },
  "442470": {
    "x": 1006,
    "y": 386,
    "visible": true,
    "action": "air"
  },
  "442471": {
    "x": 999,
    "y": 379,
    "visible": true,
    "action": "air"
  },
  "442472": {
    "x": 994,
    "y": 373,
    "visible": true,
    "action": "air"
  },
  "442473": {
    "x": 987,
    "y": 367,
    "visible": true,
    "action": "air"
  },
  "442474": {
    "x": 982,
    "y": 362,
    "visible": true,
    "action": "air"
  },
  "442475": {
    "x": 977,
    "y": 357,
    "visible": true,
    "action": "air"
  },
  "442476": {
    "x": 973,
    "y": 353,
    "visible": true,
    "action": "air"
  },
  "442477": {
    "x": 968,
    "y": 350,
    "visible": true,
    "action": "air"
  },
  "442478": {
    "x": 963,
    "y": 345,
    "visible": true,
    "action": "air"
  },
  "442479": {
    "x": 962,
    "y": 342,
    "visible": true,
    "action": "air"
  },
  "442480": {
    "x": 953,
    "y": 339,
    "visible": true,
    "action": "air"
  },
  "442481": {
    "x": 945,
    "y": 334,
    "visible": true,
    "action": "air"
  },
  "442482": {
    "x": null,
    "y": null,
    "visible": false,
    "action": "air"
  },
  "442483": {
    "x": null,
    "y": null,
    "visible": false,
    "action": "air"
  },
  "442484": {
    "x": null,
    "y": null,
    "visible": false,
    "action": "air"
  },
  "442485": {
    "x": null,
    "y": null,
    "visible": false,
    "action": "air"
  },
  "442486": {
    "x": null,
    "y": null,
    "visible": false,
    "action": "air"
  },
  "442487": {
    "x": null,
    "y": null,
    "visible": false,
    "action": "air"
  },
  "442488": {
    "x": null,
    "y": null,
    "visible": false,
    "action": "air"
  },
  "442489": {
    "x": null,
    "y": null,
    "visible": false,
    "action": "air"
  },
  "442490": {
    "x": null,
    "y": null,
    "visible": false,
    "action": "air"
  },
  "442491": {
    "x": null,
    "y": null,
    "visible": false,
    "action": "air"
  },
  "442492": {
    "x": null,
    "y": null,
    "visible": false,
    "action": "air"
  },
  "442493": {
    "x": null,
    "y": null,
    "visible": false,
    "action": "air"
  },
  "442494": {
    "x": null,
    "y": null,
    "visible": false,
    "action": "air"
  },
  "442495": {
    "x": null,
    "y": null,
    "visible": false,
    "action": "air"
  },
  "442496": {
    "x": null,
    "y": null,
    "visible": false,
    "action": "air"
  },
  "442497": {
    "x": null,
    "y": null,
    "visible": false,
    "action": "air"
  },
  "442498": {
    "x": null,
    "y": null,
    "visible": false,
    "action": "air"
  },
  "442499": {
    "x": 888,
    "y": 347,
    "visible": true,
    "action": "air"
  },
  "442500": {
    "x": 887,
    "y": 347,
    "visible": true,
    "action": "air"
  },
  "442501": {
    "x": 883.6106719367585,
    "y": 337.800395256917,
    "visible": true,
    "action": "bounce"
  },
  "442502": {
    "x": 882,
    "y": 330,
    "visible": true,
    "action": "air"
  },
  "442503": {
    "x": null,
    "y": null,
    "visible": false,
    "action": "air"
  },
  "442504": {
    "x": 878.867588932806,
    "y": 314.084980237154,
    "visible": true,
    "action": "hit"
  },
  "442505": {
    "x": null,
    "y": null,
    "visible": false,
    "action": "air"
  },
  "442506": {
    "x": 874,
    "y": 310,
    "visible": true,
    "action": "air"
  },
  "442507": {
    "x": 866,
    "y": 310,
    "visible": true,
    "action": "air"
  },
  "442508": {
    "x": 864,
    "y": 309,
    "visible": true,
    "action": "air"
  },
  "442509": {
    "x": 860,
    "y": 310,
    "visible": true,
    "action": "air"
  },
  "442510": {
    "x": 855,
    "y": 309,
    "visible": true,
    "action": "air"
  },
  "442511": {
    "x": 851,
    "y": 309,
    "visible": true,
    "action": "air"
  },
  "442512": {
    "x": 849,
    "y": 310,
    "visible": true,
    "action": "air"
  },
  "442513": {
    "x": 838,
    "y": 309,
    "visible": true,
    "action": "air"
  },
  "442514": {
    "x": 835,
    "y": 312,
    "visible": true,
    "action": "air"
  },
  "442515": {
    "x": null,
    "y": null,
    "visible": false,
    "action": "air"
  },
  "442516": {
    "x": 831,
    "y": 317,
    "visible": true,
    "action": "air"
  },
  "442517": {
    "x": 827,
    "y": 318,
    "visible": true,
    "action": "air"
  },
  "442518": {
    "x": 825,
    "y": 321,
    "visible": true,
    "action": "air"
  },
  "442519": {
    "x": 821,
    "y": 325,
    "visible": true,
    "action": "air"
  },
  "442520": {
    "x": 817,
    "y": 328,
    "visible": true,
    "action": "air"
  },
  "442521": {
    "x": 813,
    "y": 333,
    "visible": true,
    "action": "air"
  },
  "442522": {
    "x": 808,
    "y": 335,
    "visible": true,
    "action": "air"
  },
  "442523": {
    "x": 805,
    "y": 341,
    "visible": true,
    "action": "air"
  },
  "442524": {
    "x": 800,
    "y": 345,
    "visible": true,
    "action": "air"
  },
  "442525": {
    "x": 797,
    "y": 351,
    "visible": true,
    "action": "air"
  },
  "442526": {
    "x": 793,
    "y": 357,
    "visible": true,
    "action": "air"
  },
  "442527": {
    "x": 789,
    "y": 363,
    "visible": true,
    "action": "air"
  },
  "442528": {
    "x": 785,
    "y": 370,
    "visible": true,
    "action": "air"
  },
  "442529": {
    "x": 783,
    "y": 376,
    "visible": true,
    "action": "air"
  },
  "442530": {
    "x": 776,
    "y": 384,
    "visible": true,
    "action": "air"
  },
  "442531": {
    "x": 772,
    "y": 392,
    "visible": true,
    "action": "air"
  },
  "442532": {
    "x": 769,
    "y": 400,
    "visible": true,
    "action": "air"
  },
  "442533": {
    "x": 765,
    "y": 407,
    "visible": true,
    "action": "air"
  },
  "442534": {
    "x": 760,
    "y": 417,
    "visible": true,
    "action": "air"
  },
  "442535": {
    "x": 757,
    "y": 427,
    "visible": true,
    "action": "air"
  },
  "442536": {
    "x": 753,
    "y": 438,
    "visible": true,
    "action": "air"
  },
  "442537": {
    "x": 747,
    "y": 450,
    "visible": true,
    "action": "air"
  },
  "442538": {
    "x": 744,
    "y": 460,
    "visible": true,
    "action": "air"
  },
  "442539": {
    "x": 740,
    "y": 471,
    "visible": true,
    "action": "air"
  },
  "442540": {
    "x": 736,
    "y": 483,
    "visible": true,
    "action": "air"
  },
  "442541": {
    "x": 732,
    "y": 496,
    "visible": true,
    "action": "air"
  },
  "442542": {
    "x": 729,
    "y": 507,
    "visible": true,
    "action": "air"
  },
  "442543": {
    "x": 724,
    "y": 522,
    "visible": true,
    "action": "air"
  },
  "442544": {
    "x": 717,
    "y": 536,
    "visible": true,
    "action": "air"
  },
  "442545": {
    "x": 716,
    "y": 552,
    "visible": true,
    "action": "air"
  },
  "442546": {
    "x": 711,
    "y": 571,
    "visible": true,
    "action": "air"
  },
  "442547": {
    "x": 710,
    "y": 583,
    "visible": true,
    "action": "air"
  },
  "442548": {
    "x": 704,
    "y": 596,
    "visible": true,
    "action": "air"
  },
  "442549": {
    "x": 700,
    "y": 613,
    "visible": true,
    "action": "air"
  },
  "442550": {
    "x": 696,
    "y": 634,
    "visible": true,
    "action": "air"
  },
  "442551": {
    "x": 693,
    "y": 652,
    "visible": true,
    "action": "air"
  },
  "442552": {
    "x": 686.772727272727,
    "y": 662.701581027668,
    "visible": true,
    "action": "bounce"
  },
  "442553": {
    "x": 683,
    "y": 672,
    "visible": true,
    "action": "air"
  },
  "442554": {
    "x": 679,
    "y": 667,
    "visible": true,
    "action": "air"
  },
  "442555": {
    "x": 673,
    "y": 665,
    "visible": true,
    "action": "air"
  },
  "442556": {
    "x": 670,
    "y": 659,
    "visible": true,
    "action": "air"
  },
  "442557": {
    "x": 668,
    "y": 658,
    "visible": true,
    "action": "air"
  },
  "442558": {
    "x": 664,
    "y": 658,
    "visible": true,
    "action": "air"
  },
  "442559": {
    "x": 656,
    "y": 656,
    "visible": true,
    "action": "air"
  },
  "442560": {
    "x": 654,
    "y": 656,
    "visible": true,
    "action": "air"
  },
  "442561": {
    "x": 650,
    "y": 655,
    "visible": true,
    "action": "air"
  },
  "442562": {
    "x": 644,
    "y": 655,
    "visible": true,
    "action": "air"
  },
  "442563": {
    "x": 640,
    "y": 655,
    "visible": true,
    "action": "air"
  },
  "442564": {
    "x": 636,
    "y": 657,
    "visible": true,
    "action": "air"
  },
  "442565": {
    "x": 632,
    "y": 658,
    "visible": true,
    "action": "air"
  },
  "442566": {
    "x": 624,
    "y": 662,
    "visible": true,
    "action": "air"
  },
  "442567": {
    "x": 620,
    "y": 664,
    "visible": true,
    "action": "air"
  },
  "442568": {
    "x": 615,
    "y": 665,
    "visible": true,
    "action": "air"
  },
  "442569": {
    "x": 611,
    "y": 667,
    "visible": true,
    "action": "air"
  },
  "442570": {
    "x": 607,
    "y": 671,
    "visible": true,
    "action": "air"
  },
  "442571": {
    "x": 603,
    "y": 675,
    "visible": true,
    "action": "air"
  },
  "442572": {
    "x": 595,
    "y": 679,
    "visible": true,
    "action": "air"
  },
  "442573": {
    "x": 592,
    "y": 685,
    "visible": true,
    "action": "air"
  },
  "442574": {
    "x": 587,
    "y": 691,
    "visible": true,
    "action": "air"
  },
  "442575": {
    "x": 582,
    "y": 696,
    "visible": true,
    "action": "air"
  },
  "442576": {
    "x": 577,
    "y": 704,
    "visible": true,
    "action": "air"
  },
  "442577": {
    "x": 574,
    "y": 710,
    "visible": true,
    "action": "air"
  },
  "442578": {
    "x": 566,
    "y": 717,
    "visible": true,
    "action": "air"
  },
  "442579": {
    "x": 562,
    "y": 727,
    "visible": true,
    "action": "air"
  },
  "442580": {
    "x": 553.9664031620553,
    "y": 724.3616600790513,
    "visible": true,
    "action": "hit"
  },
  "442581": {
    "x": null,
    "y": null,
    "visible": false,
    "action": "air"
  },
  "442582": {
    "x": 613,
    "y": 680,
    "visible": true,
    "action": "air"
  },
  "442583": {
    "x": 646,
    "y": 648,
    "visible": true,
    "action": "air"
  },
  "442584": {
    "x": 670,
    "y": 624,
    "visible": true,
    "action": "air"
  },
  "442585": {
    "x": 684,
    "y": 611,
    "visible": true,
    "action": "air"
  },
  "442586": {
    "x": 722,
    "y": 579,
    "visible": true,
    "action": "air"
  },
  "442587": {
    "x": 735,
    "y": 564,
    "visible": true,
    "action": "air"
  },
  "442588": {
    "x": 756,
    "y": 547,
    "visible": true,
    "action": "air"
  },
  "442589": {
    "x": 782,
    "y": 528,
    "visible": true,
    "action": "air"
  },
  "442590": {
    "x": 798,
    "y": 512,
    "visible": true,
    "action": "air"
  },
  "442591": {
    "x": 812,
    "y": 503,
    "visible": true,
    "action": "air"
  },
  "442592": {
    "x": 830,
    "y": 484,
    "visible": true,
    "action": "air"
  },
  "442593": {
    "x": 845,
    "y": 475,
    "visible": true,
    "action": "air"
  },
  "442594": {
    "x": 859,
    "y": 466,
    "visible": true,
    "action": "air"
  },
  "442595": {
    "x": 877,
    "y": 449,
    "visible": true,
    "action": "air"
  },
  "442596": {
    "x": 889,
    "y": 445,
    "visible": true,
    "action": "air"
  },
  "442597": {
    "x": 896,
    "y": 439,
    "visible": true,
    "action": "air"
  },
  "442598": {
    "x": 913,
    "y": 430,
    "visible": true,
    "action": "air"
  },
  "442599": {
    "x": 923,
    "y": 422,
    "visible": true,
    "action": "air"
  },
  "442600": {
    "x": 936,
    "y": 418,
    "visible": true,
    "action": "air"
  },
  "442601": {
    "x": 946,
    "y": 413,
    "visible": true,
    "action": "air"
  },
  "442602": {
    "x": 954,
    "y": 406,
    "visible": true,
    "action": "air"
  },
  "442603": {
    "x": 965,
    "y": 404,
    "visible": true,
    "action": "air"
  },
  "442604": {
    "x": 975,
    "y": 400,
    "visible": true,
    "action": "air"
  },
  "442605": {
    "x": 982,
    "y": 396,
    "visible": true,
    "action": "air"
  },
  "442606": {
    "x": 993,
    "y": 395,
    "visible": true,
    "action": "air"
  },
  "442607": {
    "x": 1002,
    "y": 391,
    "visible": true,
    "action": "air"
  },
  "442608": {
    "x": 1007,
    "y": 389,
    "visible": true,
    "action": "air"
  },
  "442609": {
    "x": 1014,
    "y": 389,
    "visible": true,
    "action": "air"
  },
  "442610": {
    "x": 1023,
    "y": 389,
    "visible": true,
    "action": "air"
  },
  "442611": {
    "x": 1028,
    "y": 387,
    "visible": true,
    "action": "air"
  },
  "442612": {
    "x": 1035,
    "y": 388,
    "visible": true,
    "action": "air"
  },
  "442613": {
    "x": 1041,
    "y": 390,
    "visible": true,
    "action": "air"
  },
  "442614": {
    "x": 1044.875494071146,
    "y": 378.11660079051376,
    "visible": true,
    "action": "bounce"
  },
  "442615": {
    "x": 1053,
    "y": 384,
    "visible": true,
    "action": "air"
  },
  "442616": {
    "x": 1056,
    "y": 374,
    "visible": true,
    "action": "air"
  },
  "442617": {
    "x": 1060,
    "y": 364,
    "visible": true,
    "action": "air"
  },
  "442618": {
    "x": 1064,
    "y": 355,
    "visible": true,
    "action": "air"
  },
  "442619": {
    "x": 1068,
    "y": 345,
    "visible": true,
    "action": "air"
  },
  "442620": {
    "x": null,
    "y": null,
    "visible": false,
    "action": "air"
  },
  "442621": {
    "x": null,
    "y": null,
    "visible": false,
    "action": "air"
  },
  "442622": {
    "x": null,
    "y": null,
    "visible": false,
    "action": "air"
  },
  "442623": {
    "x": null,
    "y": null,
    "visible": false,
    "action": "air"
  },
  "442624": {
    "x": null,
    "y": null,
    "visible": false,
    "action": "air"
  },
  "442625": {
    "x": null,
    "y": null,
    "visible": false,
    "action": "air"
  },
  "442626": {
    "x": null,
    "y": null,
    "visible": false,
    "action": "air"
  },
  "442627": {
    "x": null,
    "y": null,
    "visible": false,
    "action": "air"
  },
  "442628": {
    "x": null,
    "y": null,
    "visible": false,
    "action": "air"
  },
  "442629": {
    "x": null,
    "y": null,
    "visible": false,
    "action": "air"
  },
  "442630": {
    "x": null,
    "y": null,
    "visible": false,
    "action": "air"
  },
  "442631": {
    "x": null,
    "y": null,
    "visible": false,
    "action": "air"
  },
  "442632": {
    "x": 652,
    "y": 727,
    "visible": true,
    "action": "air"
  },
  "442633": {
    "x": null,
    "y": null,
    "visible": false,
    "action": "air"
  },
  "442634": {
    "x": null,
    "y": null,
    "visible": false,
    "action": "air"
  },
  "442635": {
    "x": null,
    "y": null,
    "visible": false,
    "action": "air"
  },
  "442636": {
    "x": null,
    "y": null,
    "visible": false,
    "action": "air"
  },
  "442637": {
    "x": 1120.764822134387,
    "y": 247.68181818181802,
    "visible": true,
    "action": "hit"
  },
  "442638": {
    "x": null,
    "y": null,
    "visible": false,
    "action": "air"
  },
  "442639": {
    "x": null,
    "y": null,
    "visible": false,
    "action": "air"
  },
  "442640": {
    "x": null,
    "y": null,
    "visible": false,
    "action": "air"
  },
  "442641": {
    "x": null,
    "y": null,
    "visible": false,
    "action": "air"
  },
  "442642": {
    "x": null,
    "y": null,
    "visible": false,
    "action": "air"
  },
  "442643": {
    "x": null,
    "y": null,
    "visible": false,
    "action": "air"
  },
  "442644": {
    "x": null,
    "y": null,
    "visible": false,
    "action": "air"
  },
  "442645": {
    "x": null,
    "y": null,
    "visible": false,
    "action": "air"
  },
  "442646": {
    "x": null,
    "y": null,
    "visible": false,
    "action": "air"
  },
  "442647": {
    "x": null,
    "y": null,
    "visible": false,
    "action": "air"
  },
  "442648": {
    "x": null,
    "y": null,
    "visible": false,
    "action": "air"
  },
  "442649": {
    "x": null,
    "y": null,
    "visible": false,
    "action": "air"
  },
  "442650": {
    "x": 1042,
    "y": 297,
    "visible": true,
    "action": "air"
  },
  "442651": {
    "x": 1036,
    "y": 303,
    "visible": true,
    "action": "air"
  },
  "442652": {
    "x": 1030,
    "y": 308,
    "visible": true,
    "action": "air"
  },
  "442653": {
    "x": 1024,
    "y": 316,
    "visible": true,
    "action": "air"
  },
  "442654": {
    "x": 1016,
    "y": 323,
    "visible": true,
    "action": "air"
  },
  "442655": {
    "x": 1012,
    "y": 329,
    "visible": true,
    "action": "air"
  },
  "442656": {
    "x": 1005,
    "y": 335,
    "visible": true,
    "action": "air"
  },
  "442657": {
    "x": 997,
    "y": 347,
    "visible": true,
    "action": "air"
  },
  "442658": {
    "x": 987,
    "y": 355,
    "visible": true,
    "action": "air"
  },
  "442659": {
    "x": 983,
    "y": 365,
    "visible": true,
    "action": "air"
  },
  "442660": {
    "x": 977,
    "y": 375,
    "visible": true,
    "action": "air"
  },
  "442661": {
    "x": 969,
    "y": 386,
    "visible": true,
    "action": "air"
  },
  "442662": {
    "x": 964,
    "y": 396,
    "visible": true,
    "action": "air"
  },
  "442663": {
    "x": 954,
    "y": 407,
    "visible": true,
    "action": "air"
  },
  "442664": {
    "x": 948,
    "y": 421,
    "visible": true,
    "action": "air"
  },
  "442665": {
    "x": 941,
    "y": 435,
    "visible": true,
    "action": "air"
  },
  "442666": {
    "x": 933,
    "y": 446,
    "visible": true,
    "action": "air"
  },
  "442667": {
    "x": 924,
    "y": 459,
    "visible": true,
    "action": "air"
  },
  "442668": {
    "x": 919,
    "y": 474,
    "visible": true,
    "action": "air"
  },
  "442669": {
    "x": 910,
    "y": 489,
    "visible": true,
    "action": "air"
  },
  "442670": {
    "x": 902,
    "y": 506,
    "visible": true,
    "action": "air"
  },
  "442671": {
    "x": 895,
    "y": 520,
    "visible": true,
    "action": "air"
  },
  "442672": {
    "x": 887,
    "y": 537,
    "visible": true,
    "action": "air"
  },
  "442673": {
    "x": 877,
    "y": 558,
    "visible": true,
    "action": "air"
  },
  "442674": {
    "x": 873,
    "y": 574,
    "visible": true,
    "action": "air"
  },
  "442675": {
    "x": 861,
    "y": 592,
    "visible": true,
    "action": "air"
  },
  "442676": {
    "x": 852,
    "y": 616,
    "visible": true,
    "action": "air"
  },
  "442677": {
    "x": 845,
    "y": 635,
    "visible": true,
    "action": "air"
  },
  "442678": {
    "x": 835,
    "y": 653,
    "visible": true,
    "action": "air"
  },
  "442679": {
    "x": 827,
    "y": 677,
    "visible": true,
    "action": "air"
  },
  "442680": {
    "x": 819,
    "y": 697,
    "visible": true,
    "action": "air"
  },
  "442681": {
    "x": 805,
    "y": 723,
    "visible": true,
    "action": "air"
  },
  "442682": {
    "x": 799,
    "y": 749,
    "visible": true,
    "action": "air"
  },
  "442683": {
    "x": 788.749011857707,
    "y": 752.820158102767,
    "visible": true,
    "action": "bounce"
  },
  "442684": {
    "x": 786,
    "y": 756,
    "visible": true,
    "action": "air"
  },
  "442685": {
    "x": 776,
    "y": 753,
    "visible": true,
    "action": "air"
  },
  "442686": {
    "x": 772,
    "y": 753,
    "visible": true,
    "action": "air"
  },
  "442687": {
    "x": 764,
    "y": 749,
    "visible": true,
    "action": "air"
  },
  "442688": {
    "x": 756,
    "y": 749,
    "visible": true,
    "action": "air"
  },
  "442689": {
    "x": null,
    "y": null,
    "visible": false,
    "action": "air"
  },
  "442690": {
    "x": null,
    "y": null,
    "visible": false,
    "action": "air"
  },
  "442691": {
    "x": null,
    "y": null,
    "visible": false,
    "action": "air"
  },
  "442692": {
    "x": 728,
    "y": 748,
    "visible": true,
    "action": "air"
  },
  "442693": {
    "x": 722,
    "y": 752,
    "visible": true,
    "action": "air"
  },
  "442694": {
    "x": 711,
    "y": 753,
    "visible": true,
    "action": "air"
  },
  "442695": {
    "x": 705,
    "y": 754,
    "visible": true,
    "action": "air"
  },
  "442696": {
    "x": 697,
    "y": 757,
    "visible": true,
    "action": "air"
  },
  "442697": {
    "x": 687,
    "y": 761,
    "visible": true,
    "action": "air"
  },
  "442698": {
    "x": null,
    "y": null,
    "visible": false,
    "action": "air"
  },
  "442699": {
    "x": 677.286561264822,
    "y": 759.9347826086955,
    "visible": true,
    "action": "hit"
  },
  "442700": {
    "x": null,
    "y": null,
    "visible": false,
    "action": "air"
  },
  "442701": {
    "x": 724,
    "y": 695,
    "visible": true,
    "action": "air"
  },
  "442702": {
    "x": 740,
    "y": 675,
    "visible": true,
    "action": "air"
  },
  "442703": {
    "x": 762,
    "y": 641,
    "visible": true,
    "action": "air"
  },
  "442704": {
    "x": 774,
    "y": 622,
    "visible": true,
    "action": "air"
  },
  "442705": {
    "x": 790,
    "y": 602,
    "visible": true,
    "action": "air"
  },
  "442706": {
    "x": 809,
    "y": 577,
    "visible": true,
    "action": "air"
  },
  "442707": {
    "x": 822,
    "y": 560,
    "visible": true,
    "action": "air"
  },
  "442708": {
    "x": 833,
    "y": 544,
    "visible": true,
    "action": "air"
  },
  "442709": {
    "x": 849,
    "y": 527,
    "visible": true,
    "action": "air"
  },
  "442710": {
    "x": 858,
    "y": 514,
    "visible": true,
    "action": "air"
  },
  "442711": {
    "x": 866,
    "y": 502,
    "visible": true,
    "action": "air"
  },
  "442712": {
    "x": 880,
    "y": 487,
    "visible": true,
    "action": "air"
  },
  "442713": {
    "x": 890,
    "y": 476,
    "visible": true,
    "action": "air"
  },
  "442714": {
    "x": 896,
    "y": 467,
    "visible": true,
    "action": "air"
  },
  "442715": {
    "x": 909,
    "y": 455,
    "visible": true,
    "action": "air"
  },
  "442716": {
    "x": 917,
    "y": 449,
    "visible": true,
    "action": "air"
  },
  "442717": {
    "x": 923,
    "y": 442,
    "visible": true,
    "action": "air"
  },
  "442718": {
    "x": 934,
    "y": 432,
    "visible": true,
    "action": "air"
  },
  "442719": {
    "x": 939,
    "y": 426,
    "visible": true,
    "action": "air"
  },
  "442720": {
    "x": 946,
    "y": 421,
    "visible": true,
    "action": "air"
  },
  "442721": {
    "x": 954,
    "y": 417,
    "visible": true,
    "action": "air"
  },
  "442722": {
    "x": 955,
    "y": 410,
    "visible": true,
    "action": "air"
  },
  "442723": {
    "x": 965,
    "y": 408,
    "visible": true,
    "action": "air"
  },
  "442724": {
    "x": 971,
    "y": 403,
    "visible": true,
    "action": "air"
  },
  "442725": {
    "x": 975,
    "y": 399,
    "visible": true,
    "action": "air"
  },
  "442726": {
    "x": 981,
    "y": 398,
    "visible": true,
    "action": "air"
  },
  "442727": {
    "x": 985,
    "y": 395,
    "visible": true,
    "action": "air"
  },
  "442728": {
    "x": 988,
    "y": 392,
    "visible": true,
    "action": "air"
  },
  "442729": {
    "x": 994,
    "y": 393,
    "visible": true,
    "action": "air"
  },
  "442730": {
    "x": 1000,
    "y": 389,
    "visible": true,
    "action": "air"
  },
  "442731": {
    "x": 1000,
    "y": 388,
    "visible": true,
    "action": "air"
  },
  "442732": {
    "x": 1006,
    "y": 389,
    "visible": true,
    "action": "air"
  },
  "442733": {
    "x": 1012,
    "y": 389,
    "visible": true,
    "action": "air"
  },
  "442734": {
    "x": 1013,
    "y": 388,
    "visible": true,
    "action": "air"
  },
  "442735": {
    "x": 1015,
    "y": 389,
    "visible": true,
    "action": "air"
  },
  "442736": {
    "x": 1021.160079051383,
    "y": 385.23122529644274,
    "visible": true,
    "action": "bounce"
  },
  "442737": {
    "x": 1023,
    "y": 391,
    "visible": true,
    "action": "air"
  },
  "442738": {
    "x": 1025,
    "y": 382,
    "visible": true,
    "action": "air"
  },
  "442739": {
    "x": 1027,
    "y": 372,
    "visible": true,
    "action": "air"
  },
  "442740": {
    "x": 1029,
    "y": 364,
    "visible": true,
    "action": "air"
  },
  "442741": {
    "x": 1031,
    "y": 354,
    "visible": true,
    "action": "air"
  },
  "442742": {
    "x": 1034,
    "y": 345,
    "visible": true,
    "action": "air"
  },
  "442743": {
    "x": 1035,
    "y": 338,
    "visible": true,
    "action": "air"
  },
  "442744": {
    "x": 1039,
    "y": 332,
    "visible": true,
    "action": "air"
  },
  "442745": {
    "x": 1041,
    "y": 323,
    "visible": true,
    "action": "air"
  },
  "442746": {
    "x": 1041,
    "y": 316,
    "visible": true,
    "action": "air"
  },
  "442747": {
    "x": 1043,
    "y": 307,
    "visible": true,
    "action": "air"
  },
  "442748": {
    "x": 1045,
    "y": 301,
    "visible": true,
    "action": "air"
  },
  "442749": {
    "x": 1045,
    "y": 297,
    "visible": true,
    "action": "air"
  },
  "442750": {
    "x": 1046,
    "y": 293,
    "visible": true,
    "action": "air"
  },
  "442751": {
    "x": 1048,
    "y": 287,
    "visible": true,
    "action": "air"
  },
  "442752": {
    "x": 1047,
    "y": 282,
    "visible": true,
    "action": "air"
  },
  "442753": {
    "x": null,
    "y": null,
    "visible": false,
    "action": "air"
  },
  "442754": {
    "x": 1055,
    "y": 273,
    "visible": true,
    "action": "air"
  },
  "442755": {
    "x": 1057,
    "y": 270,
    "visible": true,
    "action": "air"
  },
  "442756": {
    "x": null,
    "y": null,
    "visible": false,
    "action": "air"
  },
  "442757": {
    "x": null,
    "y": null,
    "visible": false,
    "action": "air"
  },
  "442758": {
    "x": null,
    "y": null,
    "visible": false,
    "action": "air"
  },
  "442759": {
    "x": null,
    "y": null,
    "visible": false,
    "action": "air"
  },
  "442760": {
    "x": null,
    "y": null,
    "visible": false,
    "action": "air"
  },
  "442761": {
    "x": null,
    "y": null,
    "visible": false,
    "action": "air"
  },
  "442762": {
    "x": 1063.847826086956,
    "y": 247.68181818181802,
    "visible": true,
    "action": "hit"
  },
  "442763": {
    "x": null,
    "y": null,
    "visible": false,
    "action": "air"
  },
  "442764": {
    "x": 1076,
    "y": 267,
    "visible": true,
    "action": "air"
  },
  "442765": {
    "x": 1084,
    "y": 272,
    "visible": true,
    "action": "air"
  },
  "442766": {
    "x": 1089,
    "y": 276,
    "visible": true,
    "action": "air"
  },
  "442767": {
    "x": 1092,
    "y": 282,
    "visible": true,
    "action": "air"
  },
  "442768": {
    "x": 1097,
    "y": 288,
    "visible": true,
    "action": "air"
  },
  "442769": {
    "x": 1103,
    "y": 295,
    "visible": true,
    "action": "air"
  },
  "442770": {
    "x": null,
    "y": null,
    "visible": false,
    "action": "air"
  },
  "442771": {
    "x": null,
    "y": null,
    "visible": false,
    "action": "air"
  },
  "442772": {
    "x": null,
    "y": null,
    "visible": false,
    "action": "air"
  },
  "442773": {
    "x": 1118,
    "y": 327,
    "visible": true,
    "action": "air"
  },
  "442774": {
    "x": 1123,
    "y": 337,
    "visible": true,
    "action": "air"
  },
  "442775": {
    "x": 1130,
    "y": 347,
    "visible": true,
    "action": "air"
  },
  "442776": {
    "x": 1132,
    "y": 356,
    "visible": true,
    "action": "air"
  },
  "442777": {
    "x": 1135,
    "y": 368,
    "visible": true,
    "action": "air"
  },
  "442778": {
    "x": 1143,
    "y": 378,
    "visible": true,
    "action": "air"
  },
  "442779": {
    "x": 1145,
    "y": 393,
    "visible": true,
    "action": "air"
  },
  "442780": {
    "x": 1151,
    "y": 406,
    "visible": true,
    "action": "air"
  },
  "442781": {
    "x": 1157,
    "y": 419,
    "visible": true,
    "action": "air"
  },
  "442782": {
    "x": 1160,
    "y": 436,
    "visible": true,
    "action": "air"
  },
  "442783": {
    "x": 1165,
    "y": 451,
    "visible": true,
    "action": "air"
  },
  "442784": {
    "x": 1167,
    "y": 469,
    "visible": true,
    "action": "air"
  },
  "442785": {
    "x": 1176,
    "y": 485,
    "visible": true,
    "action": "air"
  },
  "442786": {
    "x": 1182,
    "y": 503,
    "visible": true,
    "action": "air"
  },
  "442787": {
    "x": 1189,
    "y": 524,
    "visible": true,
    "action": "air"
  },
  "442788": {
    "x": 1191,
    "y": 542,
    "visible": true,
    "action": "air"
  },
  "442789": {
    "x": 1195,
    "y": 563,
    "visible": true,
    "action": "air"
  },
  "442790": {
    "x": 1205,
    "y": 586,
    "visible": true,
    "action": "air"
  },
  "442791": {
    "x": 1207,
    "y": 607,
    "visible": true,
    "action": "air"
  },
  "442792": {
    "x": 1213,
    "y": 628,
    "visible": true,
    "action": "air"
  },
  "442793": {
    "x": 1221,
    "y": 655,
    "visible": true,
    "action": "air"
  },
  "442794": {
    "x": 1223,
    "y": 682,
    "visible": true,
    "action": "air"
  },
  "442795": {
    "x": 1226,
    "y": 704,
    "visible": true,
    "action": "air"
  },
  "442796": {
    "x": 1238,
    "y": 736,
    "visible": true,
    "action": "air"
  },
  "442797": {
    "x": 1234.5988142292485,
    "y": 745.705533596838,
    "visible": true,
    "action": "bounce"
  },
  "442798": {
    "x": 1245,
    "y": 747,
    "visible": true,
    "action": "air"
  },
  "442799": {
    "x": 1251,
    "y": 748,
    "visible": true,
    "action": "air"
  },
  "442800": {
    "x": 1254,
    "y": 748,
    "visible": true,
    "action": "air"
  },
  "442801": {
    "x": 1263,
    "y": 752,
    "visible": true,
    "action": "air"
  },
  "442802": {
    "x": 1267,
    "y": 755,
    "visible": true,
    "action": "air"
  },
  "442803": {
    "x": 1270,
    "y": 756,
    "visible": true,
    "action": "air"
  },
  "442804": {
    "x": 1276,
    "y": 761,
    "visible": true,
    "action": "air"
  },
  "442805": {
    "x": 1282,
    "y": 766,
    "visible": true,
    "action": "air"
  },
  "442806": {
    "x": 1285,
    "y": 769,
    "visible": true,
    "action": "air"
  },
  "442807": {
    "x": 1294,
    "y": 776,
    "visible": true,
    "action": "air"
  },
  "442808": {
    "x": 1300,
    "y": 783,
    "visible": true,
    "action": "air"
  },
  "442809": {
    "x": 1302,
    "y": 788,
    "visible": true,
    "action": "air"
  },
  "442810": {
    "x": 1310,
    "y": 796,
    "visible": true,
    "action": "air"
  },
  "442811": {
    "x": 1316,
    "y": 806,
    "visible": true,
    "action": "air"
  },
  "442812": {
    "x": null,
    "y": null,
    "visible": false,
    "action": "air"
  },
  "442813": {
    "x": 1324.7173913043475,
    "y": 814.4802371541502,
    "visible": true,
    "action": "hit"
  },
  "442814": {
    "x": null,
    "y": null,
    "visible": false,
    "action": "air"
  },
  "442815": {
    "x": 1255,
    "y": 724,
    "visible": true,
    "action": "air"
  },
  "442816": {
    "x": 1236,
    "y": 699,
    "visible": true,
    "action": "air"
  },
  "442817": {
    "x": 1208,
    "y": 666,
    "visible": true,
    "action": "air"
  },
  "442818": {
    "x": 1184,
    "y": 637,
    "visible": true,
    "action": "air"
  },
  "442819": {
    "x": 1169,
    "y": 619,
    "visible": true,
    "action": "air"
  },
  "442820": {
    "x": 1147,
    "y": 591,
    "visible": true,
    "action": "air"
  },
  "442821": {
    "x": 1128,
    "y": 568,
    "visible": true,
    "action": "air"
  },
  "442822": {
    "x": 1113,
    "y": 556,
    "visible": true,
    "action": "air"
  },
  "442823": {
    "x": 1095,
    "y": 535,
    "visible": true,
    "action": "air"
  },
  "442824": {
    "x": 1081,
    "y": 519,
    "visible": true,
    "action": "air"
  },
  "442825": {
    "x": 1068,
    "y": 507,
    "visible": true,
    "action": "air"
  },
  "442826": {
    "x": 1051,
    "y": 495,
    "visible": true,
    "action": "air"
  },
  "442827": {
    "x": 1038,
    "y": 478,
    "visible": true,
    "action": "air"
  },
  "442828": {
    "x": 1025,
    "y": 469,
    "visible": true,
    "action": "air"
  },
  "442829": {
    "x": 1011,
    "y": 459,
    "visible": true,
    "action": "air"
  },
  "442830": {
    "x": 1000,
    "y": 448,
    "visible": true,
    "action": "air"
  },
  "442831": {
    "x": 986,
    "y": 442,
    "visible": true,
    "action": "air"
  },
  "442832": {
    "x": 977,
    "y": 433,
    "visible": true,
    "action": "air"
  },
  "442833": {
    "x": 965,
    "y": 425,
    "visible": true,
    "action": "air"
  },
  "442834": {
    "x": 955,
    "y": 419,
    "visible": true,
    "action": "air"
  },
  "442835": {
    "x": 947,
    "y": 415,
    "visible": true,
    "action": "air"
  },
  "442836": {
    "x": 938,
    "y": 411,
    "visible": true,
    "action": "air"
  },
  "442837": {
    "x": 925,
    "y": 406,
    "visible": true,
    "action": "air"
  },
  "442838": {
    "x": 918,
    "y": 402,
    "visible": true,
    "action": "air"
  },
  "442839": {
    "x": 911,
    "y": 398,
    "visible": true,
    "action": "air"
  },
  "442840": {
    "x": 903,
    "y": 396,
    "visible": true,
    "action": "air"
  },
  "442841": {
    "x": 893,
    "y": 393,
    "visible": true,
    "action": "air"
  },
  "442842": {
    "x": 887,
    "y": 389,
    "visible": true,
    "action": "air"
  },
  "442843": {
    "x": 879,
    "y": 389,
    "visible": true,
    "action": "air"
  },
  "442844": {
    "x": 871,
    "y": 388,
    "visible": true,
    "action": "air"
  },
  "442845": {
    "x": 864,
    "y": 388,
    "visible": true,
    "action": "air"
  },
  "442846": {
    "x": 856,
    "y": 388,
    "visible": true,
    "action": "air"
  },
  "442847": {
    "x": 849,
    "y": 387,
    "visible": true,
    "action": "air"
  },
  "442848": {
    "x": 842,
    "y": 388,
    "visible": true,
    "action": "air"
  },
  "442849": {
    "x": 834,
    "y": 389,
    "visible": true,
    "action": "air"
  },
  "442850": {
    "x": 826.693675889328,
    "y": 380.48814229249,
    "visible": true,
    "action": "bounce"
  },
  "442851": {
    "x": 825,
    "y": 384,
    "visible": true,
    "action": "air"
  },
  "442852": {
    "x": 820,
    "y": 374,
    "visible": true,
    "action": "air"
  },
  "442853": {
    "x": 817,
    "y": 365,
    "visible": true,
    "action": "air"
  },
  "442854": {
    "x": 814,
    "y": 354,
    "visible": true,
    "action": "air"
  },
  "442855": {
    "x": 806,
    "y": 347,
    "visible": true,
    "action": "air"
  },
  "442856": {
    "x": 804,
    "y": 339,
    "visible": true,
    "action": "air"
  },
  "442857": {
    "x": 801,
    "y": 332,
    "visible": true,
    "action": "air"
  },
  "442858": {
    "x": 798,
    "y": 325,
    "visible": true,
    "action": "air"
  },
  "442859": {
    "x": 794,
    "y": 316,
    "visible": true,
    "action": "air"
  },
  "442860": {
    "x": 791,
    "y": 308,
    "visible": true,
    "action": "air"
  },
  "442861": {
    "x": 786,
    "y": 303,
    "visible": true,
    "action": "air"
  },
  "442862": {
    "x": 783,
    "y": 297,
    "visible": true,
    "action": "air"
  },
  "442863": {
    "x": 783,
    "y": 292,
    "visible": true,
    "action": "air"
  },
  "442864": {
    "x": 775,
    "y": 287,
    "visible": true,
    "action": "air"
  },
  "442865": {
    "x": 772,
    "y": 282,
    "visible": true,
    "action": "air"
  },
  "442866": {
    "x": null,
    "y": null,
    "visible": false,
    "action": "air"
  },
  "442867": {
    "x": 767.405138339921,
    "y": 264.282608695652,
    "visible": true,
    "action": "hit"
  },
  "442868": {
    "x": null,
    "y": null,
    "visible": false,
    "action": "air"
  },
  "442869": {
    "x": null,
    "y": null,
    "visible": false,
    "action": "air"
  },
  "442870": {
    "x": null,
    "y": null,
    "visible": false,
    "action": "air"
  },
  "442871": {
    "x": null,
    "y": null,
    "visible": false,
    "action": "air"
  },
  "442872": {
    "x": null,
    "y": null,
    "visible": false,
    "action": "air"
  },
  "442873": {
    "x": null,
    "y": null,
    "visible": false,
    "action": "air"
  },
  "442874": {
    "x": null,
    "y": null,
    "visible": false,
    "action": "air"
  },
  "442875": {
    "x": 861,
    "y": 288,
    "visible": true,
    "action": "air"
  },
  "442876": {
    "x": null,
    "y": null,
    "visible": false,
    "action": "air"
  },
  "442877": {
    "x": null,
    "y": null,
    "visible": false,
    "action": "air"
  },
  "442878": {
    "x": 903,
    "y": 304,
    "visible": true,
    "action": "air"
  },
  "442879": {
    "x": 919,
    "y": 308,
    "visible": true,
    "action": "air"
  },
  "442880": {
    "x": 934,
    "y": 316,
    "visible": true,
    "action": "air"
  },
  "442881": {
    "x": 942,
    "y": 319,
    "visible": true,
    "action": "air"
  },
  "442882": {
    "x": 965,
    "y": 333,
    "visible": true,
    "action": "air"
  },
  "442883": {
    "x": 977,
    "y": 339,
    "visible": true,
    "action": "air"
  },
  "442884": {
    "x": 987,
    "y": 344,
    "visible": true,
    "action": "air"
  },
  "442885": {
    "x": 1009,
    "y": 355,
    "visible": true,
    "action": "air"
  },
  "442886": {
    "x": 1025,
    "y": 365,
    "visible": true,
    "action": "air"
  },
  "442887": {
    "x": 1036,
    "y": 373,
    "visible": true,
    "action": "air"
  },
  "442888": {
    "x": 1053,
    "y": 383,
    "visible": true,
    "action": "air"
  },
  "442889": {
    "x": 1068,
    "y": 395,
    "visible": true,
    "action": "air"
  },
  "442890": {
    "x": 1082,
    "y": 405,
    "visible": true,
    "action": "air"
  },
  "442891": {
    "x": 1101,
    "y": 419,
    "visible": true,
    "action": "air"
  },
  "442892": {
    "x": 1118,
    "y": 433,
    "visible": true,
    "action": "air"
  },
  "442893": {
    "x": 1128,
    "y": 443,
    "visible": true,
    "action": "air"
  },
  "442894": {
    "x": 1149,
    "y": 459,
    "visible": true,
    "action": "air"
  },
  "442895": {
    "x": 1164,
    "y": 476,
    "visible": true,
    "action": "air"
  },
  "442896": {
    "x": 1180,
    "y": 489,
    "visible": true,
    "action": "air"
  },
  "442897": {
    "x": 1195,
    "y": 506,
    "visible": true,
    "action": "air"
  },
  "442898": {
    "x": 1217,
    "y": 526,
    "visible": true,
    "action": "air"
  },
  "442899": {
    "x": 1233,
    "y": 542,
    "visible": true,
    "action": "air"
  },
  "442900": {
    "x": 1249,
    "y": 558,
    "visible": true,
    "action": "air"
  },
  "442901": {
    "x": 1269,
    "y": 580,
    "visible": true,
    "action": "air"
  },
  "442902": {
    "x": 1282,
    "y": 597,
    "visible": true,
    "action": "air"
  },
  "442903": {
    "x": 1303,
    "y": 619,
    "visible": true,
    "action": "air"
  },
  "442904": {
    "x": 1323,
    "y": 640,
    "visible": true,
    "action": "air"
  },
  "442905": {
    "x": null,
    "y": null,
    "visible": false,
    "action": "air"
  },
  "442906": {
    "x": 1354,
    "y": 682,
    "visible": true,
    "action": "air"
  },
  "442907": {
    "x": 1355.547430830039,
    "y": 676.9308300395257,
    "visible": true,
    "action": "bounce"
  },
  "442908": {
    "x": 1375,
    "y": 682,
    "visible": true,
    "action": "air"
  },
  "442909": {
    "x": 1394,
    "y": 681,
    "visible": true,
    "action": "air"
  },
  "442910": {
    "x": 1407,
    "y": 679,
    "visible": true,
    "action": "air"
  },
  "442911": {
    "x": 1420,
    "y": 677,
    "visible": true,
    "action": "air"
  },
  "442912": {
    "x": 1433,
    "y": 678,
    "visible": true,
    "action": "air"
  },
  "442913": {
    "x": 1453,
    "y": 678,
    "visible": true,
    "action": "air"
  },
  "442914": {
    "x": 1461,
    "y": 677,
    "visible": true,
    "action": "air"
  },
  "442915": {
    "x": 1479,
    "y": 680,
    "visible": true,
    "action": "air"
  },
  "442916": {
    "x": 1495,
    "y": 682,
    "visible": true,
    "action": "air"
  },
  "442917": {
    "x": 1508,
    "y": 681,
    "visible": true,
    "action": "air"
  },
  "442918": {
    "x": 1523,
    "y": 686,
    "visible": true,
    "action": "air"
  },
  "442919": {
    "x": 1542,
    "y": 688,
    "visible": true,
    "action": "air"
  },
  "442920": {
    "x": 1552,
    "y": 691,
    "visible": true,
    "action": "air"
  },
  "442921": {
    "x": 1573,
    "y": 697,
    "visible": true,
    "action": "air"
  },
  "442922": {
    "x": 1586,
    "y": 702,
    "visible": true,
    "action": "air"
  },
  "442923": {
    "x": 1600,
    "y": 705,
    "visible": true,
    "action": "air"
  },
  "442924": {
    "x": 1622,
    "y": 714,
    "visible": true,
    "action": "air"
  },
  "442925": {
    "x": 1636,
    "y": 721,
    "visible": true,
    "action": "air"
  },
  "442926": {
    "x": 1652,
    "y": 724,
    "visible": true,
    "action": "air"
  },
  "442927": {
    "x": 1669,
    "y": 735,
    "visible": true,
    "action": "air"
  },
  "442928": {
    "x": 1688,
    "y": 745,
    "visible": true,
    "action": "air"
  },
  "442929": {
    "x": 1700,
    "y": 752,
    "visible": true,
    "action": "air"
  },
  "442930": {
    "x": 1720,
    "y": 762,
    "visible": true,
    "action": "air"
  },
  "442931": {
    "x": 1742,
    "y": 775,
    "visible": true,
    "action": "air"
  },
  "442932": {
    "x": 1753,
    "y": 783,
    "visible": true,
    "action": "air"
  },
  "442933": {
    "x": 1774,
    "y": 796,
    "visible": true,
    "action": "air"
  },
  "442934": {
    "x": 1793,
    "y": 809,
    "visible": true,
    "action": "air"
  },
  "442935": {
    "x": 1808,
    "y": 821,
    "visible": true,
    "action": "air"
  },
  "442936": {
    "x": 1826,
    "y": 836,
    "visible": true,
    "action": "air"
  },
  "442937": {
    "x": 1847,
    "y": 852,
    "visible": true,
    "action": "air"
  },
  "442938": {
    "x": 1863,
    "y": 863,
    "visible": true,
    "action": "air"
  },
  "442939": {
    "x": 1882,
    "y": 882,
    "visible": true,
    "action": "air"
  },
  "442940": {
    "x": 1900,
    "y": 894,
    "visible": true,
    "action": "air"
  },
  "442941": {
    "x": null,
    "y": null,
    "visible": false,
    "action": "air"
  },
  "442942": {
    "x": null,
    "y": null,
    "visible": false,
    "action": "air"
  },
  "442943": {
    "x": null,
    "y": null,
    "visible": false,
    "action": "air"
  },
  "442944": {
    "x": null,
    "y": null,
    "visible": false,
    "action": "air"
  },
  "442945": {
    "x": null,
    "y": null,
    "visible": false,
    "action": "air"
  },
  "442946": {
    "x": null,
    "y": null,
    "visible": false,
    "action": "air"
  },
  "442947": {
    "x": null,
    "y": null,
    "visible": false,
    "action": "air"
  },
  "442948": {
    "x": null,
    "y": null,
    "visible": false,
    "action": "air"
  },
  "442949": {
    "x": null,
    "y": null,
    "visible": false,
    "action": "air"
  },
  "442950": {
    "x": null,
    "y": null,
    "visible": false,
    "action": "air"
  },
  "442951": {
    "x": null,
    "y": null,
    "visible": false,
    "action": "air"
  },
  "442952": {
    "x": null,
    "y": null,
    "visible": false,
    "action": "air"
  },
  "442953": {
    "x": null,
    "y": null,
    "visible": false,
    "action": "air"
  },
  "442954": {
    "x": null,
    "y": null,
    "visible": false,
    "action": "air"
  },
  "442955": {
    "x": null,
    "y": null,
    "visible": false,
    "action": "air"
  },
  "442956": {
    "x": null,
    "y": null,
    "visible": false,
    "action": "air"
  }
}